{
"meta":{"test_sets":[],"test_metrics":[],"learn_metrics":[{"best_value":"Min","name":"RMSE"}],"launch_mode":"Train","parameters":"","iteration_count":1000,"learn_sets":["learn"],"name":"experiment"},
"iterations":[
{"learn":[6.991941941],"iteration":0,"passed_time":0.032559125,"remaining_time":32.52656588},
{"learn":[6.98028787],"iteration":1,"passed_time":0.05150058333,"remaining_time":25.69879108},
{"learn":[6.967184447],"iteration":2,"passed_time":0.0626785,"remaining_time":20.83015483},
{"learn":[6.9556141],"iteration":3,"passed_time":0.080366625,"remaining_time":20.01128962},
{"learn":[6.944531046],"iteration":4,"passed_time":0.09297554167,"remaining_time":18.50213279},
{"learn":[6.930122172],"iteration":5,"passed_time":0.1037060833,"remaining_time":17.18064114},
{"learn":[6.917701899],"iteration":6,"passed_time":0.1127331667,"remaining_time":15.99200493},
{"learn":[6.905397428],"iteration":7,"passed_time":0.1225216667,"remaining_time":15.19268667},
{"learn":[6.892232558],"iteration":8,"passed_time":0.1307900833,"remaining_time":14.4014414},
{"learn":[6.882088237],"iteration":9,"passed_time":0.1400875417,"remaining_time":13.86866663},
{"learn":[6.870728373],"iteration":10,"passed_time":0.148088,"remaining_time":13.31445745},
{"learn":[6.860568854],"iteration":11,"passed_time":0.158028625,"remaining_time":13.01102346},
{"learn":[6.851582792],"iteration":12,"passed_time":0.1659115,"remaining_time":12.59651158},
{"learn":[6.840911257],"iteration":13,"passed_time":0.1740308333,"remaining_time":12.25674298},
{"learn":[6.832278285],"iteration":14,"passed_time":0.1814885833,"remaining_time":11.91775031},
{"learn":[6.823360039],"iteration":15,"passed_time":0.1900026667,"remaining_time":11.685164},
{"learn":[6.813769219],"iteration":16,"passed_time":0.197556375,"remaining_time":11.42340686},
{"learn":[6.805375275],"iteration":17,"passed_time":0.206963625,"remaining_time":11.29101554},
{"learn":[6.796981875],"iteration":18,"passed_time":0.215305375,"remaining_time":11.11655647},
{"learn":[6.788877466],"iteration":19,"passed_time":0.2249072917,"remaining_time":11.02045729},
{"learn":[6.780223652],"iteration":20,"passed_time":0.232115,"remaining_time":10.82098024},
{"learn":[6.773208772],"iteration":21,"passed_time":0.24126325,"remaining_time":10.72524811},
{"learn":[6.76619891],"iteration":22,"passed_time":0.25031825,"remaining_time":10.63308392},
{"learn":[6.758175727],"iteration":23,"passed_time":0.2593741667,"remaining_time":10.54788278},
{"learn":[6.751670537],"iteration":24,"passed_time":0.2680247917,"remaining_time":10.45296688},
{"learn":[6.744063365],"iteration":25,"passed_time":0.2773945,"remaining_time":10.39162473},
{"learn":[6.739063705],"iteration":26,"passed_time":0.2840950417,"remaining_time":10.23794354},
{"learn":[6.732614954],"iteration":27,"passed_time":0.2945585,"remaining_time":10.22538793},
{"learn":[6.725682776],"iteration":28,"passed_time":0.3042170833,"remaining_time":10.18602717},
{"learn":[6.718782556],"iteration":29,"passed_time":0.31177425,"remaining_time":10.08070075},
{"learn":[6.712557575],"iteration":30,"passed_time":0.320820375,"remaining_time":10.02822398},
{"learn":[6.706544354],"iteration":31,"passed_time":0.330664625,"remaining_time":10.00260491},
{"learn":[6.700049852],"iteration":32,"passed_time":0.339580125,"remaining_time":9.950726693},
{"learn":[6.693366536],"iteration":33,"passed_time":0.3480242917,"remaining_time":9.887984287},
{"learn":[6.686705304],"iteration":34,"passed_time":0.3590919583,"remaining_time":9.90067828},
{"learn":[6.681362665],"iteration":35,"passed_time":0.3710872917,"remaining_time":9.936893032},
{"learn":[6.675726819],"iteration":36,"passed_time":0.3839903333,"remaining_time":9.994126784},
{"learn":[6.670817178],"iteration":37,"passed_time":0.392418375,"remaining_time":9.934380967},
{"learn":[6.667456263],"iteration":38,"passed_time":0.3962131667,"remaining_time":9.763098799},
{"learn":[6.662141198],"iteration":39,"passed_time":0.405415125,"remaining_time":9.729963},
{"learn":[6.656568217],"iteration":40,"passed_time":0.4143593333,"remaining_time":9.69196587},
{"learn":[6.652292015],"iteration":41,"passed_time":0.4221920833,"remaining_time":9.630000377},
{"learn":[6.646642599],"iteration":42,"passed_time":0.4306435417,"remaining_time":9.584322544},
{"learn":[6.642538107],"iteration":43,"passed_time":0.439843375,"remaining_time":9.556596966},
{"learn":[6.637519189],"iteration":44,"passed_time":0.449286625,"remaining_time":9.534860597},
{"learn":[6.632323028],"iteration":45,"passed_time":0.4586747083,"remaining_time":9.512514603},
{"learn":[6.627187228],"iteration":46,"passed_time":0.468859,"remaining_time":9.506864404},
{"learn":[6.622658248],"iteration":47,"passed_time":0.4775955,"remaining_time":9.47231075},
{"learn":[6.618247076],"iteration":48,"passed_time":0.4870967083,"remaining_time":9.453652441},
{"learn":[6.613467092],"iteration":49,"passed_time":0.4952414167,"remaining_time":9.409586917},
{"learn":[6.608504942],"iteration":50,"passed_time":0.5051110417,"remaining_time":9.39902703},
{"learn":[6.605017366],"iteration":51,"passed_time":0.513642,"remaining_time":9.364088769},
{"learn":[6.600634269],"iteration":52,"passed_time":0.5218116667,"remaining_time":9.323691478},
{"learn":[6.596988009],"iteration":53,"passed_time":0.5315959583,"remaining_time":9.31277364},
{"learn":[6.593515693],"iteration":54,"passed_time":0.53906075,"remaining_time":9.262043795},
{"learn":[6.589332277],"iteration":55,"passed_time":0.5502341667,"remaining_time":9.275375952},
{"learn":[6.584616055],"iteration":56,"passed_time":0.5590898333,"remaining_time":9.249503734},
{"learn":[6.580732665],"iteration":57,"passed_time":0.568810125,"remaining_time":9.238260996},
{"learn":[6.577481742],"iteration":58,"passed_time":0.5777483333,"remaining_time":9.214596299},
{"learn":[6.575001075],"iteration":59,"passed_time":0.5868163333,"remaining_time":9.193455889},
{"learn":[6.571014061],"iteration":60,"passed_time":0.5941674167,"remaining_time":9.146282037},
{"learn":[6.567707144],"iteration":61,"passed_time":0.60415725,"remaining_time":9.140314524},
{"learn":[6.564578816],"iteration":62,"passed_time":0.6117847083,"remaining_time":9.099083678},
{"learn":[6.561780705],"iteration":63,"passed_time":0.621740375,"remaining_time":9.092952984},
{"learn":[6.558293223],"iteration":64,"passed_time":0.63050525,"remaining_time":9.069575519},
{"learn":[6.555216877],"iteration":65,"passed_time":0.6394435,"remaining_time":9.049094379},
{"learn":[6.552374082],"iteration":66,"passed_time":0.6470616667,"remaining_time":9.010575149},
{"learn":[6.549613106],"iteration":67,"passed_time":0.6551903333,"remaining_time":8.979961627},
{"learn":[6.547041566],"iteration":68,"passed_time":0.66399075,"remaining_time":8.959063598},
{"learn":[6.543790204],"iteration":69,"passed_time":0.6733450417,"remaining_time":8.945869839},
{"learn":[6.541014454],"iteration":70,"passed_time":0.6824564583,"remaining_time":8.929606335},
{"learn":[6.538122514],"iteration":71,"passed_time":0.69022625,"remaining_time":8.896249444},
{"learn":[6.534598631],"iteration":72,"passed_time":0.7012540833,"remaining_time":8.904966236},
{"learn":[6.531790296],"iteration":73,"passed_time":0.7109813333,"remaining_time":8.896874523},
{"learn":[6.529180829],"iteration":74,"passed_time":0.7204490417,"remaining_time":8.885538181},
{"learn":[6.526806949],"iteration":75,"passed_time":0.73177925,"remaining_time":8.896895092},
{"learn":[6.524465027],"iteration":76,"passed_time":0.74038775,"remaining_time":8.875037575},
{"learn":[6.52247912],"iteration":77,"passed_time":0.749890625,"remaining_time":8.864091747},
{"learn":[6.520072687],"iteration":78,"passed_time":0.7579950417,"remaining_time":8.836878903},
{"learn":[6.517686278],"iteration":79,"passed_time":0.767398625,"remaining_time":8.825084188},
{"learn":[6.514737437],"iteration":80,"passed_time":0.7755787917,"remaining_time":8.799468019},
{"learn":[6.512256236],"iteration":81,"passed_time":0.7857637917,"remaining_time":8.796721473},
{"learn":[6.509576828],"iteration":82,"passed_time":0.8022050417,"remaining_time":8.862915942},
{"learn":[6.506962832],"iteration":83,"passed_time":0.810913125,"remaining_time":8.842814554},
{"learn":[6.504182823],"iteration":84,"passed_time":0.819279,"remaining_time":8.819297471},
{"learn":[6.502155667],"iteration":85,"passed_time":0.825696875,"remaining_time":8.775429578},
{"learn":[6.4999932],"iteration":86,"passed_time":0.8345820417,"remaining_time":8.758314989},
{"learn":[6.49806621],"iteration":87,"passed_time":0.8423506667,"remaining_time":8.729816},
{"learn":[6.496225999],"iteration":88,"passed_time":0.8507400833,"remaining_time":8.708137257},
{"learn":[6.493824438],"iteration":89,"passed_time":0.8584920833,"remaining_time":8.680308843},
{"learn":[6.492260647],"iteration":90,"passed_time":0.8693204167,"remaining_time":8.683651195},
{"learn":[6.490157276],"iteration":91,"passed_time":0.8795611667,"remaining_time":8.680886297},
{"learn":[6.488294385],"iteration":92,"passed_time":0.8887853333,"remaining_time":8.668046208},
{"learn":[6.485737701],"iteration":93,"passed_time":0.899869375,"remaining_time":8.673209082},
{"learn":[6.483455169],"iteration":94,"passed_time":0.9080930833,"remaining_time":8.650781478},
{"learn":[6.480691505],"iteration":95,"passed_time":0.9176497917,"remaining_time":8.641202205},
{"learn":[6.478718139],"iteration":96,"passed_time":0.9260752083,"remaining_time":8.621091888},
{"learn":[6.476805268],"iteration":97,"passed_time":0.93579725,"remaining_time":8.613154281},
{"learn":[6.475230609],"iteration":98,"passed_time":0.9432935833,"remaining_time":8.58492443},
{"learn":[6.473320525],"iteration":99,"passed_time":0.9519580833,"remaining_time":8.56762275},
{"learn":[6.471755088],"iteration":100,"passed_time":0.9610685,"remaining_time":8.554461203},
{"learn":[6.469470692],"iteration":101,"passed_time":0.9710622917,"remaining_time":8.549156254},
{"learn":[6.46772016],"iteration":102,"passed_time":0.9833815,"remaining_time":8.564011704},
{"learn":[6.465886463],"iteration":103,"passed_time":1.028002292,"remaining_time":8.856635128},
{"learn":[6.464339766],"iteration":104,"passed_time":1.067932,"remaining_time":9.102848952},
{"learn":[6.462452843],"iteration":105,"passed_time":1.09261425,"remaining_time":9.215067354},
{"learn":[6.460760025],"iteration":106,"passed_time":1.161418125,"remaining_time":9.692956875},
{"learn":[6.459005883],"iteration":107,"passed_time":1.20247,"remaining_time":9.931511481},
{"learn":[6.456834175],"iteration":108,"passed_time":1.246451375,"remaining_time":10.18888234},
{"learn":[6.454889231],"iteration":109,"passed_time":1.326054333,"remaining_time":10.72898506},
{"learn":[6.452149719],"iteration":110,"passed_time":1.360863,"remaining_time":10.89916403},
{"learn":[6.450692291],"iteration":111,"passed_time":1.383580708,"remaining_time":10.96981847},
{"learn":[6.449056467],"iteration":112,"passed_time":1.395210833,"remaining_time":10.95178769},
{"learn":[6.446888868],"iteration":113,"passed_time":1.419795708,"remaining_time":11.03455261},
{"learn":[6.444861216],"iteration":114,"passed_time":1.43316575,"remaining_time":11.02914512},
{"learn":[6.44317205],"iteration":115,"passed_time":1.44580125,"remaining_time":11.01800263},
{"learn":[6.443152354],"iteration":116,"passed_time":1.453984458,"remaining_time":10.97323313},
{"learn":[6.441540941],"iteration":117,"passed_time":1.467324667,"remaining_time":10.96763014},
{"learn":[6.439601231],"iteration":118,"passed_time":1.500291292,"remaining_time":11.10719855},
{"learn":[6.438107918],"iteration":119,"passed_time":1.527682917,"remaining_time":11.20300806},
{"learn":[6.436878207],"iteration":120,"passed_time":1.546736792,"remaining_time":11.2362119},
{"learn":[6.435709089],"iteration":121,"passed_time":1.571393958,"remaining_time":11.30888439},
{"learn":[6.434690433],"iteration":122,"passed_time":1.587896792,"remaining_time":11.32183322},
{"learn":[6.43319025],"iteration":123,"passed_time":1.597479708,"remaining_time":11.28542117},
{"learn":[6.430937378],"iteration":124,"passed_time":1.614676833,"remaining_time":11.30273783},
{"learn":[6.429614059],"iteration":125,"passed_time":1.628917583,"remaining_time":11.29899974},
{"learn":[6.427478097],"iteration":126,"passed_time":1.639563708,"remaining_time":11.27038675},
{"learn":[6.426519411],"iteration":127,"passed_time":1.64839425,"remaining_time":11.22968583},
{"learn":[6.425803989],"iteration":128,"passed_time":1.653387875,"remaining_time":11.1635724},
{"learn":[6.424236659],"iteration":129,"passed_time":1.663329667,"remaining_time":11.13151392},
{"learn":[6.422369281],"iteration":130,"passed_time":1.670752667,"remaining_time":11.08308448},
{"learn":[6.420935309],"iteration":131,"passed_time":1.678878667,"remaining_time":11.03989911},
{"learn":[6.420863743],"iteration":132,"passed_time":1.6874325,"remaining_time":11.00002991},
{"learn":[6.419664378],"iteration":133,"passed_time":1.697265333,"remaining_time":10.96889387},
{"learn":[6.418900528],"iteration":134,"passed_time":1.705159792,"remaining_time":10.92565348},
{"learn":[6.417192225],"iteration":135,"passed_time":1.714105833,"remaining_time":10.88961353},
{"learn":[6.415961435],"iteration":136,"passed_time":1.723100708,"remaining_time":10.85427672},
{"learn":[6.415471853],"iteration":137,"passed_time":1.728234458,"remaining_time":10.79520365},
{"learn":[6.413412651],"iteration":138,"passed_time":1.736622833,"remaining_time":10.75706662},
{"learn":[6.412140776],"iteration":139,"passed_time":1.746762208,"remaining_time":10.73011071},
{"learn":[6.411283066],"iteration":140,"passed_time":1.756881458,"remaining_time":10.70327073},
{"learn":[6.410483605],"iteration":141,"passed_time":1.774427,"remaining_time":10.72153779},
{"learn":[6.409246568],"iteration":142,"passed_time":1.78484275,"remaining_time":10.69657508},
{"learn":[6.407645839],"iteration":143,"passed_time":1.797271875,"remaining_time":10.68378281},
{"learn":[6.406045532],"iteration":144,"passed_time":1.807164958,"remaining_time":10.65604165},
{"learn":[6.405263979],"iteration":145,"passed_time":1.81593825,"remaining_time":10.62199497},
{"learn":[6.404096901],"iteration":146,"passed_time":1.826279083,"remaining_time":10.59738815},
{"learn":[6.402744077],"iteration":147,"passed_time":1.836689333,"remaining_time":10.57337373},
{"learn":[6.401026923],"iteration":148,"passed_time":1.84586825,"remaining_time":10.54250927},
{"learn":[6.400424838],"iteration":149,"passed_time":1.8558765,"remaining_time":10.5166335},
{"learn":[6.399282958],"iteration":150,"passed_time":1.865536042,"remaining_time":10.48900728},
{"learn":[6.398568956],"iteration":151,"passed_time":1.875047292,"remaining_time":10.46079015},
{"learn":[6.397105513],"iteration":152,"passed_time":1.884950208,"remaining_time":10.43498579},
{"learn":[6.395296663],"iteration":153,"passed_time":1.8978695,"remaining_time":10.42595842},
{"learn":[6.39320727],"iteration":154,"passed_time":1.909968708,"remaining_time":10.41241006},
{"learn":[6.392106651],"iteration":155,"passed_time":1.921723,"remaining_time":10.39701418},
{"learn":[6.391810039],"iteration":156,"passed_time":1.932396542,"remaining_time":10.37586169},
{"learn":[6.390717858],"iteration":157,"passed_time":1.94267,"remaining_time":10.35270975},
{"learn":[6.390024562],"iteration":158,"passed_time":1.95303375,"remaining_time":10.33019738},
{"learn":[6.388865778],"iteration":159,"passed_time":1.965916708,"remaining_time":10.32106272},
{"learn":[6.387347077],"iteration":160,"passed_time":1.988098667,"remaining_time":10.36034026},
{"learn":[6.386367967],"iteration":161,"passed_time":2.003775833,"remaining_time":10.36521079},
{"learn":[6.384972866],"iteration":162,"passed_time":2.013337583,"remaining_time":10.33842673},
{"learn":[6.383521144],"iteration":163,"passed_time":2.023828958,"remaining_time":10.31659152},
{"learn":[6.382572385],"iteration":164,"passed_time":2.032134833,"remaining_time":10.28383385},
{"learn":[6.381386343],"iteration":165,"passed_time":2.042471125,"remaining_time":10.2615718},
{"learn":[6.38078145],"iteration":166,"passed_time":2.051610458,"remaining_time":10.23348211},
{"learn":[6.380261316],"iteration":167,"passed_time":2.059684125,"remaining_time":10.20034043},
{"learn":[6.37953827],"iteration":168,"passed_time":2.068828458,"remaining_time":10.17276005},
{"learn":[6.378140048],"iteration":169,"passed_time":2.077500667,"remaining_time":10.14309149},
{"learn":[6.376448014],"iteration":170,"passed_time":2.086153292,"remaining_time":10.11357356},
{"learn":[6.375036361],"iteration":171,"passed_time":2.095849167,"remaining_time":10.08932041},
{"learn":[6.374901623],"iteration":172,"passed_time":2.1049025,"remaining_time":10.06216397},
{"learn":[6.373988646],"iteration":173,"passed_time":2.113116667,"remaining_time":10.03123199},
{"learn":[6.37367907],"iteration":174,"passed_time":2.122633583,"remaining_time":10.00670118},
{"learn":[6.372503689],"iteration":175,"passed_time":2.131206792,"remaining_time":9.977922706},
{"learn":[6.371727079],"iteration":176,"passed_time":2.138982958,"remaining_time":9.945666524},
{"learn":[6.370630888],"iteration":177,"passed_time":2.14818575,"remaining_time":9.92027352},
{"learn":[6.369552365],"iteration":178,"passed_time":2.157438417,"remaining_time":9.895290168},
{"learn":[6.36856924],"iteration":179,"passed_time":2.165965708,"remaining_time":9.867177116},
{"learn":[6.367588362],"iteration":180,"passed_time":2.174629125,"remaining_time":9.839896427},
{"learn":[6.36668746],"iteration":181,"passed_time":2.183324125,"remaining_time":9.812962276},
{"learn":[6.365279358],"iteration":182,"passed_time":2.192925667,"remaining_time":9.790274698},
{"learn":[6.363555365],"iteration":183,"passed_time":2.203163375,"remaining_time":9.77055062},
{"learn":[6.362041667],"iteration":184,"passed_time":2.21241925,"remaining_time":9.746603723},
{"learn":[6.361085667],"iteration":185,"passed_time":2.221730667,"remaining_time":9.723057864},
{"learn":[6.359978557],"iteration":186,"passed_time":2.22936775,"remaining_time":9.692384924},
{"learn":[6.358803314],"iteration":187,"passed_time":2.238667208,"remaining_time":9.669137091},
{"learn":[6.357063398],"iteration":188,"passed_time":2.2471625,"remaining_time":9.642586177},
{"learn":[6.35547066],"iteration":189,"passed_time":2.256221708,"remaining_time":9.618629388},
{"learn":[6.3542502],"iteration":190,"passed_time":2.265164625,"remaining_time":9.594336029},
{"learn":[6.352317285],"iteration":191,"passed_time":2.27635675,"remaining_time":9.57966799},
{"learn":[6.35120282],"iteration":192,"passed_time":2.285100417,"remaining_time":9.554798115},
{"learn":[6.350925982],"iteration":193,"passed_time":2.294256917,"remaining_time":9.531809664},
{"learn":[6.349880151],"iteration":194,"passed_time":2.303537792,"remaining_time":9.509476525},
{"learn":[6.349552142],"iteration":195,"passed_time":2.312541792,"remaining_time":9.486140819},
{"learn":[6.348257109],"iteration":196,"passed_time":2.322763167,"remaining_time":9.467912806},
{"learn":[6.348200917],"iteration":197,"passed_time":2.331611208,"remaining_time":9.444202975},
{"learn":[6.346696278],"iteration":198,"passed_time":2.341644167,"remaining_time":9.425411947},
{"learn":[6.34606714],"iteration":199,"passed_time":2.3514925,"remaining_time":9.40597},
{"learn":[6.345144286],"iteration":200,"passed_time":2.360067417,"remaining_time":9.381561522},
{"learn":[6.344652689],"iteration":201,"passed_time":2.36948425,"remaining_time":9.3606358},
{"learn":[6.343528997],"iteration":202,"passed_time":2.377468542,"remaining_time":9.334199151},
{"learn":[6.342567443],"iteration":203,"passed_time":2.388032,"remaining_time":9.318007216},
{"learn":[6.341520868],"iteration":204,"passed_time":2.396164292,"remaining_time":9.292442009},
{"learn":[6.341079096],"iteration":205,"passed_time":2.406788083,"remaining_time":9.276649214},
{"learn":[6.340133374],"iteration":206,"passed_time":2.415060167,"remaining_time":9.25189716},
{"learn":[6.338952177],"iteration":207,"passed_time":2.425120083,"remaining_time":9.234111087},
{"learn":[6.338453698],"iteration":208,"passed_time":2.4343805,"remaining_time":9.213373089},
{"learn":[6.337161105],"iteration":209,"passed_time":2.443091208,"remaining_time":9.19067645},
{"learn":[6.335379688],"iteration":210,"passed_time":2.453445167,"remaining_time":9.174257045},
{"learn":[6.33512389],"iteration":211,"passed_time":2.462170292,"remaining_time":9.151840518},
{"learn":[6.333627428],"iteration":212,"passed_time":2.47045625,"remaining_time":9.1279299},
{"learn":[6.332527677],"iteration":213,"passed_time":2.479600417,"remaining_time":9.107317418},
{"learn":[6.331480495],"iteration":214,"passed_time":2.488474042,"remaining_time":9.085823827},
{"learn":[6.330062769],"iteration":215,"passed_time":2.496897583,"remaining_time":9.062813451},
{"learn":[6.329299704],"iteration":216,"passed_time":2.505075333,"remaining_time":9.039050627},
{"learn":[6.329043448],"iteration":217,"passed_time":2.515251708,"remaining_time":9.022600165},
{"learn":[6.328688609],"iteration":218,"passed_time":2.527371042,"remaining_time":9.013135998},
{"learn":[6.327584742],"iteration":219,"passed_time":2.5368675,"remaining_time":8.994348409},
{"learn":[6.326523489],"iteration":220,"passed_time":2.545958875,"remaining_time":8.97421703},
{"learn":[6.325252588],"iteration":221,"passed_time":2.555528375,"remaining_time":8.955860702},
{"learn":[6.32480766],"iteration":222,"passed_time":2.564316333,"remaining_time":8.934860049},
{"learn":[6.323669773],"iteration":223,"passed_time":2.573369625,"remaining_time":8.914887629},
{"learn":[6.322420451],"iteration":224,"passed_time":2.583628542,"remaining_time":8.899164977},
{"learn":[6.321371186],"iteration":225,"passed_time":2.594672958,"remaining_time":8.88618084},
{"learn":[6.320459085],"iteration":226,"passed_time":2.604261417,"remaining_time":8.868255837},
{"learn":[6.319659488],"iteration":227,"passed_time":2.612938417,"remaining_time":8.847317797},
{"learn":[6.319323564],"iteration":228,"passed_time":2.621865917,"remaining_time":8.827330226},
{"learn":[6.318384411],"iteration":229,"passed_time":2.630646375,"remaining_time":8.80694656},
{"learn":[6.317448201],"iteration":230,"passed_time":2.638991417,"remaining_time":8.78521385},
{"learn":[6.316317789],"iteration":231,"passed_time":2.649301458,"remaining_time":8.770101379},
{"learn":[6.315986954],"iteration":232,"passed_time":2.657612167,"remaining_time":8.748448634},
{"learn":[6.314494649],"iteration":233,"passed_time":2.667201417,"remaining_time":8.731095236},
{"learn":[6.314031623],"iteration":234,"passed_time":2.678182583,"remaining_time":8.718339048},
{"learn":[6.313010355],"iteration":235,"passed_time":2.688147208,"remaining_time":8.702307064},
{"learn":[6.311772334],"iteration":236,"passed_time":2.697699875,"remaining_time":8.68500002},
{"learn":[6.310812199],"iteration":237,"passed_time":2.706510583,"remaining_time":8.665382624},
{"learn":[6.310339262],"iteration":238,"passed_time":2.714933042,"remaining_time":8.644619434},
{"learn":[6.308727065],"iteration":239,"passed_time":2.72344725,"remaining_time":8.624249625},
{"learn":[6.30721527],"iteration":240,"passed_time":2.733037,"remaining_time":8.60736549},
{"learn":[6.306947212],"iteration":241,"passed_time":2.741543417,"remaining_time":8.587148388},
{"learn":[6.306085563],"iteration":242,"passed_time":2.7508155,"remaining_time":8.569412895},
{"learn":[6.30485508],"iteration":243,"passed_time":2.75955025,"remaining_time":8.550081922},
{"learn":[6.304572773],"iteration":244,"passed_time":2.767616833,"remaining_time":8.528778405},
{"learn":[6.303138089],"iteration":245,"passed_time":2.778194583,"remaining_time":8.515279333},
{"learn":[6.302220154],"iteration":246,"passed_time":2.789755833,"remaining_time":8.504802196},
{"learn":[6.301634755],"iteration":247,"passed_time":2.798813208,"remaining_time":8.486723922},
{"learn":[6.300981739],"iteration":248,"passed_time":2.808937167,"remaining_time":8.471934989},
{"learn":[6.300204996],"iteration":249,"passed_time":2.819768875,"remaining_time":8.459306625},
{"learn":[6.300194434],"iteration":250,"passed_time":2.826926083,"remaining_time":8.435727635},
{"learn":[6.298646754],"iteration":251,"passed_time":2.837621583,"remaining_time":8.422781525},
{"learn":[6.29770825],"iteration":252,"passed_time":2.847492667,"remaining_time":8.407419059},
{"learn":[6.297264604],"iteration":253,"passed_time":2.857096917,"remaining_time":8.391316141},
{"learn":[6.296235863],"iteration":254,"passed_time":2.868021292,"remaining_time":8.379121029},
{"learn":[6.29604453],"iteration":255,"passed_time":2.878303208,"remaining_time":8.365068699},
{"learn":[6.295336422],"iteration":256,"passed_time":2.888065125,"remaining_time":8.349542365},
{"learn":[6.294147152],"iteration":257,"passed_time":2.898189458,"remaining_time":8.335103016},
{"learn":[6.29202127],"iteration":258,"passed_time":2.907775417,"remaining_time":8.319156694},
{"learn":[6.291732677],"iteration":259,"passed_time":2.918837042,"remaining_time":8.307459272},
{"learn":[6.291153109],"iteration":260,"passed_time":2.92731575,"remaining_time":8.288453407},
{"learn":[6.290743075],"iteration":261,"passed_time":2.936641875,"remaining_time":8.2719149},
{"learn":[6.290222215],"iteration":262,"passed_time":2.945765833,"remaining_time":8.254864712},
{"learn":[6.289214841],"iteration":263,"passed_time":2.955796792,"remaining_time":8.240403177},
{"learn":[6.288510336],"iteration":264,"passed_time":2.965169417,"remaining_time":8.224149137},
{"learn":[6.28767889],"iteration":265,"passed_time":2.973894875,"remaining_time":8.206161046},
{"learn":[6.286547115],"iteration":266,"passed_time":2.983589083,"remaining_time":8.190901865},
{"learn":[6.286385943],"iteration":267,"passed_time":2.986088333,"remaining_time":8.156032313},
{"learn":[6.285982104],"iteration":268,"passed_time":2.99622475,"remaining_time":8.14215722},
{"learn":[6.285053356],"iteration":269,"passed_time":3.004338167,"remaining_time":8.122840228},
{"learn":[6.284130945],"iteration":270,"passed_time":3.013909208,"remaining_time":8.107526985},
{"learn":[6.283733229],"iteration":271,"passed_time":3.0226345,"remaining_time":8.089992338},
{"learn":[6.282349085],"iteration":272,"passed_time":3.032466667,"remaining_time":8.075469841},
{"learn":[6.28203561],"iteration":273,"passed_time":3.041701042,"remaining_time":8.059397651},
{"learn":[6.281387474],"iteration":274,"passed_time":3.050675,"remaining_time":8.042688636},
{"learn":[6.280893686],"iteration":275,"passed_time":3.059077458,"remaining_time":8.024536521},
{"learn":[6.280470992],"iteration":276,"passed_time":3.06629325,"remaining_time":8.003357472},
{"learn":[6.279852363],"iteration":277,"passed_time":3.074487542,"remaining_time":7.984820162},
{"learn":[6.278987193],"iteration":278,"passed_time":3.082812792,"remaining_time":7.966695422},
{"learn":[6.278298599],"iteration":279,"passed_time":3.09197375,"remaining_time":7.950789643},
{"learn":[6.277329012],"iteration":280,"passed_time":3.099248208,"remaining_time":7.930104846},
{"learn":[6.276951449],"iteration":281,"passed_time":3.106002625,"remaining_time":7.908191081},
{"learn":[6.275760846],"iteration":282,"passed_time":3.115620375,"remaining_time":7.893638901},
{"learn":[6.27575933],"iteration":283,"passed_time":3.119482,"remaining_time":7.864609549},
{"learn":[6.275618682],"iteration":284,"passed_time":3.1276235,"remaining_time":7.846494044},
{"learn":[6.274786669],"iteration":285,"passed_time":3.135999083,"remaining_time":7.829032677},
{"learn":[6.274065365],"iteration":286,"passed_time":3.144482458,"remaining_time":7.811902414},
{"learn":[6.272556948],"iteration":287,"passed_time":3.153161458,"remaining_time":7.795315828},
{"learn":[6.271800481],"iteration":288,"passed_time":3.162276333,"remaining_time":7.779856308},
{"learn":[6.270864951],"iteration":289,"passed_time":3.170056375,"remaining_time":7.761172504},
{"learn":[6.270459394],"iteration":290,"passed_time":3.176892958,"remaining_time":7.740264974},
{"learn":[6.269468555],"iteration":291,"passed_time":3.185626833,"remaining_time":7.724054103},
{"learn":[6.268083942],"iteration":292,"passed_time":3.193327875,"remaining_time":7.705402074},
{"learn":[6.267204023],"iteration":293,"passed_time":3.202380333,"remaining_time":7.69006978},
{"learn":[6.26665731],"iteration":294,"passed_time":3.211141125,"remaining_time":7.674083028},
{"learn":[6.265636713],"iteration":295,"passed_time":3.220233625,"remaining_time":7.658934027},
{"learn":[6.265185548],"iteration":296,"passed_time":3.228174792,"remaining_time":7.641100601},
{"learn":[6.264199136],"iteration":297,"passed_time":3.236406917,"remaining_time":7.624018978},
{"learn":[6.263714654],"iteration":298,"passed_time":3.244326917,"remaining_time":7.606264778},
{"learn":[6.26328061],"iteration":299,"passed_time":3.251982375,"remaining_time":7.587958875},
{"learn":[6.262089199],"iteration":300,"passed_time":3.260143625,"remaining_time":7.570898319},
{"learn":[6.260942579],"iteration":301,"passed_time":3.268463958,"remaining_time":7.554264381},
{"learn":[6.26018997],"iteration":302,"passed_time":3.27649825,"remaining_time":7.537027328},
{"learn":[6.25931431],"iteration":303,"passed_time":3.285049292,"remaining_time":7.521033905},
{"learn":[6.258316572],"iteration":304,"passed_time":3.293513542,"remaining_time":7.504891513},
{"learn":[6.257743244],"iteration":305,"passed_time":3.301233417,"remaining_time":7.487111082},
{"learn":[6.256177037],"iteration":306,"passed_time":3.309599292,"remaining_time":7.470854427},
{"learn":[6.255103585],"iteration":307,"passed_time":3.318127417,"remaining_time":7.455013547},
{"learn":[6.254462298],"iteration":308,"passed_time":3.326599917,"remaining_time":7.439095607},
{"learn":[6.25445039],"iteration":309,"passed_time":3.333354292,"remaining_time":7.419401488},
{"learn":[6.253974887],"iteration":310,"passed_time":3.354621,"remaining_time":7.431941701},
{"learn":[6.253195643],"iteration":311,"passed_time":3.364115958,"remaining_time":7.418306985},
{"learn":[6.252707381],"iteration":312,"passed_time":3.372967583,"remaining_time":7.403286677},
{"learn":[6.252707321],"iteration":313,"passed_time":3.375589208,"remaining_time":7.374694895},
{"learn":[6.25231354],"iteration":314,"passed_time":3.383467417,"remaining_time":7.357698985},
{"learn":[6.251892674],"iteration":315,"passed_time":3.391982125,"remaining_time":7.342138524},
{"learn":[6.251314082],"iteration":316,"passed_time":3.399843625,"remaining_time":7.325215129},
{"learn":[6.25104225],"iteration":317,"passed_time":3.407997917,"remaining_time":7.308976664},
{"learn":[6.25032175],"iteration":318,"passed_time":3.415345917,"remaining_time":7.291067615},
{"learn":[6.24932838],"iteration":319,"passed_time":3.423219167,"remaining_time":7.274340729},
{"learn":[6.248987162],"iteration":320,"passed_time":3.430711208,"remaining_time":7.256862649},
{"learn":[6.248759002],"iteration":321,"passed_time":3.437665583,"remaining_time":7.238314489},
{"learn":[6.247374522],"iteration":322,"passed_time":3.445916708,"remaining_time":7.222556073},
{"learn":[6.246627088],"iteration":323,"passed_time":3.454596458,"remaining_time":7.20773829},
{"learn":[6.245790648],"iteration":324,"passed_time":3.463018833,"remaining_time":7.192423731},
{"learn":[6.245378184],"iteration":325,"passed_time":3.470095917,"remaining_time":7.174370085},
{"learn":[6.24526438],"iteration":326,"passed_time":3.477118667,"remaining_time":7.156271751},
{"learn":[6.244682249],"iteration":327,"passed_time":3.485053167,"remaining_time":7.140108927},
{"learn":[6.243805861],"iteration":328,"passed_time":3.492325792,"remaining_time":7.122646219},
{"learn":[6.243080033],"iteration":329,"passed_time":3.499148333,"remaining_time":7.104331465},
{"learn":[6.242335779],"iteration":330,"passed_time":3.506595708,"remaining_time":7.08734903},
{"learn":[6.241855983],"iteration":331,"passed_time":3.515238583,"remaining_time":7.072829439},
{"learn":[6.240581263],"iteration":332,"passed_time":3.523046417,"remaining_time":7.056672552},
{"learn":[6.239449594],"iteration":333,"passed_time":3.532110292,"remaining_time":7.043070222},
{"learn":[6.238695458],"iteration":334,"passed_time":3.540122208,"remaining_time":7.027406772},
{"learn":[6.23793786],"iteration":335,"passed_time":3.55150475,"remaining_time":7.018449863},
{"learn":[6.237899287],"iteration":336,"passed_time":3.56053125,"remaining_time":7.004843379},
{"learn":[6.237238992],"iteration":337,"passed_time":3.57214325,"remaining_time":6.996327904},
{"learn":[6.236744068],"iteration":338,"passed_time":3.582468708,"remaining_time":6.985285594},
{"learn":[6.235654984],"iteration":339,"passed_time":3.591744792,"remaining_time":6.972210478},
{"learn":[6.234349474],"iteration":340,"passed_time":3.600352417,"remaining_time":6.957865814},
{"learn":[6.233676606],"iteration":341,"passed_time":3.608499042,"remaining_time":6.942667747},
{"learn":[6.233574866],"iteration":342,"passed_time":3.615820208,"remaining_time":6.92592967},
{"learn":[6.233269228],"iteration":343,"passed_time":3.62416025,"remaining_time":6.911189314},
{"learn":[6.232743591],"iteration":344,"passed_time":3.631179167,"remaining_time":6.893977838},
{"learn":[6.232381949],"iteration":345,"passed_time":3.639846667,"remaining_time":6.879941387},
{"learn":[6.231520295],"iteration":346,"passed_time":3.647041667,"remaining_time":6.863164866},
{"learn":[6.231222597],"iteration":347,"passed_time":3.654929958,"remaining_time":6.847742336},
{"learn":[6.230450103],"iteration":348,"passed_time":3.663826042,"remaining_time":6.834242846},
{"learn":[6.229680929],"iteration":349,"passed_time":3.672813542,"remaining_time":6.820939435},
{"learn":[6.228963893],"iteration":350,"passed_time":3.680719833,"remaining_time":6.805661458},
{"learn":[6.228022835],"iteration":351,"passed_time":3.689659542,"remaining_time":6.792327793},
{"learn":[6.227279928],"iteration":352,"passed_time":3.697199,"remaining_time":6.776452558},
{"learn":[6.227248947],"iteration":353,"passed_time":3.703550125,"remaining_time":6.758455878},
{"learn":[6.227230064],"iteration":354,"passed_time":3.70768225,"remaining_time":6.736493102},
{"learn":[6.226591349],"iteration":355,"passed_time":3.715755792,"remaining_time":6.721760477},
{"learn":[6.225653497],"iteration":356,"passed_time":3.725040375,"remaining_time":6.70924639},
{"learn":[6.22521897],"iteration":357,"passed_time":3.73349225,"remaining_time":6.695257052},
{"learn":[6.224525421],"iteration":358,"passed_time":3.741960375,"remaining_time":6.681327578},
{"learn":[6.223999666],"iteration":359,"passed_time":3.750083208,"remaining_time":6.666814593},
{"learn":[6.223298232],"iteration":360,"passed_time":3.758233667,"remaining_time":6.652385909},
{"learn":[6.222269492],"iteration":361,"passed_time":3.765921583,"remaining_time":6.637176713},
{"learn":[6.2220072],"iteration":362,"passed_time":3.77401225,"remaining_time":6.622715711},
{"learn":[6.221336938],"iteration":363,"passed_time":3.782757208,"remaining_time":6.609432924},
{"learn":[6.220188312],"iteration":364,"passed_time":3.791311958,"remaining_time":6.595844092},
{"learn":[6.218898867],"iteration":365,"passed_time":3.799963792,"remaining_time":6.58245094},
{"learn":[6.217919876],"iteration":366,"passed_time":3.808366333,"remaining_time":6.568653649},
{"learn":[6.217143035],"iteration":367,"passed_time":3.815905917,"remaining_time":6.553403639},
{"learn":[6.21707503],"iteration":368,"passed_time":3.82430625,"remaining_time":6.539667327},
{"learn":[6.216588256],"iteration":369,"passed_time":3.83170975,"remaining_time":6.524262547},
{"learn":[6.21593101],"iteration":370,"passed_time":3.839937417,"remaining_time":6.510298208},
{"learn":[6.214907203],"iteration":371,"passed_time":3.847398,"remaining_time":6.495069742},
{"learn":[6.214277033],"iteration":372,"passed_time":3.856146625,"remaining_time":6.48204808},
{"learn":[6.213346579],"iteration":373,"passed_time":3.865120667,"remaining_time":6.46942657},
{"learn":[6.212591905],"iteration":374,"passed_time":3.873570458,"remaining_time":6.455950764},
{"learn":[6.2121477],"iteration":375,"passed_time":3.881659542,"remaining_time":6.441903069},
{"learn":[6.211946584],"iteration":376,"passed_time":3.889932833,"remaining_time":6.428191393},
{"learn":[6.211363347],"iteration":377,"passed_time":3.898400333,"remaining_time":6.414828062},
{"learn":[6.210488323],"iteration":378,"passed_time":3.907310333,"remaining_time":6.402215612},
{"learn":[6.20952532],"iteration":379,"passed_time":3.91555075,"remaining_time":6.388530171},
{"learn":[6.209302068],"iteration":380,"passed_time":3.923365333,"remaining_time":6.374181473},
{"learn":[6.208412793],"iteration":381,"passed_time":3.931622333,"remaining_time":6.360582728},
{"learn":[6.2080967],"iteration":382,"passed_time":3.93904475,"remaining_time":6.345667391},
{"learn":[6.207468624],"iteration":383,"passed_time":3.946675625,"remaining_time":6.331125482},
{"learn":[6.207390875],"iteration":384,"passed_time":3.955098167,"remaining_time":6.317884084},
{"learn":[6.207059224],"iteration":385,"passed_time":3.963891792,"remaining_time":6.305257928},
{"learn":[6.206405738],"iteration":386,"passed_time":3.973224375,"remaining_time":6.293505276},
{"learn":[6.206131379],"iteration":387,"passed_time":3.983996292,"remaining_time":6.284035388},
{"learn":[6.204627362],"iteration":388,"passed_time":3.993411125,"remaining_time":6.272427243},
{"learn":[6.204387911],"iteration":389,"passed_time":4.001788917,"remaining_time":6.259208306},
{"learn":[6.204070996],"iteration":390,"passed_time":4.00857625,"remaining_time":6.243536921},
{"learn":[6.203309284],"iteration":391,"passed_time":4.016741042,"remaining_time":6.23004733},
{"learn":[6.203093139],"iteration":392,"passed_time":4.025185625,"remaining_time":6.217016983},
{"learn":[6.202489335],"iteration":393,"passed_time":4.035413333,"remaining_time":6.206752487},
{"learn":[6.202368829],"iteration":394,"passed_time":4.043376417,"remaining_time":6.193019575},
{"learn":[6.201876461],"iteration":395,"passed_time":4.053367125,"remaining_time":6.182408443},
{"learn":[6.201014608],"iteration":396,"passed_time":4.061842125,"remaining_time":6.16949824},
{"learn":[6.200849331],"iteration":397,"passed_time":4.071095833,"remaining_time":6.15778817},
{"learn":[6.199513867],"iteration":398,"passed_time":4.079563417,"remaining_time":6.144906299},
{"learn":[6.198054345],"iteration":399,"passed_time":4.089672708,"remaining_time":6.134509062},
{"learn":[6.19695759],"iteration":400,"passed_time":4.097458625,"remaining_time":6.120642684},
{"learn":[6.19650364],"iteration":401,"passed_time":4.106478917,"remaining_time":6.108642767},
{"learn":[6.195930183],"iteration":402,"passed_time":4.118899833,"remaining_time":6.101695287},
{"learn":[6.195356874],"iteration":403,"passed_time":4.128842542,"remaining_time":6.09106474},
{"learn":[6.194552081],"iteration":404,"passed_time":4.137698042,"remaining_time":6.078840333},
{"learn":[6.19437835],"iteration":405,"passed_time":4.146098917,"remaining_time":6.065967381},
{"learn":[6.193877618],"iteration":406,"passed_time":4.156283,"remaining_time":6.055714543},
{"learn":[6.193291707],"iteration":407,"passed_time":4.165766625,"remaining_time":6.044445691},
{"learn":[6.193135556],"iteration":408,"passed_time":4.174142,"remaining_time":6.031584161},
{"learn":[6.192375227],"iteration":409,"passed_time":4.18382325,"remaining_time":6.020623701},
{"learn":[6.191854512],"iteration":410,"passed_time":4.192047792,"remaining_time":6.007581872},
{"learn":[6.191151193],"iteration":411,"passed_time":4.20121575,"remaining_time":5.995909857},
{"learn":[6.190489854],"iteration":412,"passed_time":4.209049333,"remaining_time":5.982353411},
{"learn":[6.189021327],"iteration":413,"passed_time":4.218638875,"remaining_time":5.971310098},
{"learn":[6.188782928],"iteration":414,"passed_time":4.226423708,"remaining_time":5.957729806},
{"learn":[6.18778314],"iteration":415,"passed_time":4.236150875,"remaining_time":5.946904113},
{"learn":[6.187759464],"iteration":416,"passed_time":4.24363475,"remaining_time":5.932947384},
{"learn":[6.186797177],"iteration":417,"passed_time":4.253152167,"remaining_time":5.921853017},
{"learn":[6.186658887],"iteration":418,"passed_time":4.260912583,"remaining_time":5.908329859},
{"learn":[6.185627058],"iteration":419,"passed_time":4.271179083,"remaining_time":5.898294925},
{"learn":[6.185370921],"iteration":420,"passed_time":4.280284208,"remaining_time":5.886661655},
{"learn":[6.184864695],"iteration":421,"passed_time":4.288568042,"remaining_time":5.873915469},
{"learn":[6.184481778],"iteration":422,"passed_time":4.295943958,"remaining_time":5.859951924},
{"learn":[6.184230536],"iteration":423,"passed_time":4.305062542,"remaining_time":5.848386849},
{"learn":[6.183878181],"iteration":424,"passed_time":4.313199625,"remaining_time":5.835505375},
{"learn":[6.182715039],"iteration":425,"passed_time":4.324320667,"remaining_time":5.826666814},
{"learn":[6.181688122],"iteration":426,"passed_time":4.336052,"remaining_time":5.818636525},
{"learn":[6.180913469],"iteration":427,"passed_time":4.348767125,"remaining_time":5.811903728},
{"learn":[6.180401441],"iteration":428,"passed_time":4.360732417,"remaining_time":5.804145011},
{"learn":[6.178945418],"iteration":429,"passed_time":4.375867125,"remaining_time":5.800568049},
{"learn":[6.177303287],"iteration":430,"passed_time":4.388618667,"remaining_time":5.793791233},
{"learn":[6.176371062],"iteration":431,"passed_time":4.402204583,"remaining_time":5.788083804},
{"learn":[6.176212735],"iteration":432,"passed_time":4.41346175,"remaining_time":5.779290559},
{"learn":[6.175896676],"iteration":433,"passed_time":4.426608,"remaining_time":5.772949604},
{"learn":[6.17527412],"iteration":434,"passed_time":4.440495708,"remaining_time":5.767540403},
{"learn":[6.174729932],"iteration":435,"passed_time":4.45393525,"remaining_time":5.761512571},
{"learn":[6.173265408],"iteration":436,"passed_time":4.468208333,"remaining_time":5.756524695},
{"learn":[6.172932755],"iteration":437,"passed_time":4.482097375,"remaining_time":5.751001655},
{"learn":[6.172639526],"iteration":438,"passed_time":4.494065167,"remaining_time":5.742985327},
{"learn":[6.17140019],"iteration":439,"passed_time":4.506224875,"remaining_time":5.735195295},
{"learn":[6.169963809],"iteration":440,"passed_time":4.518304542,"remaining_time":5.727283988},
{"learn":[6.169450707],"iteration":441,"passed_time":4.530341,"remaining_time":5.719299271},
{"learn":[6.168123291],"iteration":442,"passed_time":4.541157333,"remaining_time":5.709762155},
{"learn":[6.167746501],"iteration":443,"passed_time":4.552718,"remaining_time":5.701151369},
{"learn":[6.167500477],"iteration":444,"passed_time":4.565187708,"remaining_time":5.693661074},
{"learn":[6.166774037],"iteration":445,"passed_time":4.578445542,"remaining_time":5.687127422},
{"learn":[6.166139399],"iteration":446,"passed_time":4.590252083,"remaining_time":5.678768237},
{"learn":[6.166124081],"iteration":447,"passed_time":4.596817125,"remaining_time":5.663935386},
{"learn":[6.165433611],"iteration":448,"passed_time":4.608465375,"remaining_time":5.655377331},
{"learn":[6.164693028],"iteration":449,"passed_time":4.619771167,"remaining_time":5.646386981},
{"learn":[6.164636427],"iteration":450,"passed_time":4.632293167,"remaining_time":5.638866848},
{"learn":[6.164584027],"iteration":451,"passed_time":4.645542458,"remaining_time":5.632206343},
{"learn":[6.16355109],"iteration":452,"passed_time":4.657597625,"remaining_time":5.624074836},
{"learn":[6.162184657],"iteration":453,"passed_time":4.672551542,"remaining_time":5.619412206},
{"learn":[6.162081351],"iteration":454,"passed_time":4.684545625,"remaining_time":5.611159045},
{"learn":[6.161674821],"iteration":455,"passed_time":4.697388417,"remaining_time":5.603901971},
{"learn":[6.160692506],"iteration":456,"passed_time":4.708352583,"remaining_time":5.594388299},
{"learn":[6.159603696],"iteration":457,"passed_time":4.721986583,"remaining_time":5.588027791},
{"learn":[6.158831888],"iteration":458,"passed_time":4.734831667,"remaining_time":5.580705733},
{"learn":[6.158393978],"iteration":459,"passed_time":4.748468042,"remaining_time":5.574288571},
{"learn":[6.158222521],"iteration":460,"passed_time":4.759810875,"remaining_time":5.565158485},
{"learn":[6.157551687],"iteration":461,"passed_time":4.772556833,"remaining_time":5.557652763},
{"learn":[6.156607106],"iteration":462,"passed_time":4.787026042,"remaining_time":5.552123076},
{"learn":[6.156516549],"iteration":463,"passed_time":4.801233375,"remaining_time":5.546252347},
{"learn":[6.156460036],"iteration":464,"passed_time":4.811616125,"remaining_time":5.535945434},
{"learn":[6.155984923],"iteration":465,"passed_time":4.823562833,"remaining_time":5.527430371},
{"learn":[6.155849096],"iteration":466,"passed_time":4.830844,"remaining_time":5.5135757},
{"learn":[6.154887101],"iteration":467,"passed_time":4.843304542,"remaining_time":5.505636787},
{"learn":[6.154082361],"iteration":468,"passed_time":4.85313025,"remaining_time":5.494695443},
{"learn":[6.153300165],"iteration":469,"passed_time":4.865269042,"remaining_time":5.486367217},
{"learn":[6.152860492],"iteration":470,"passed_time":4.876997625,"remaining_time":5.477562088},
{"learn":[6.151639749],"iteration":471,"passed_time":4.891614833,"remaining_time":5.471975915},
{"learn":[6.150635398],"iteration":472,"passed_time":4.903886417,"remaining_time":5.463738143},
{"learn":[6.150165977],"iteration":473,"passed_time":4.92807775,"remaining_time":5.468710752},
{"learn":[6.149845539],"iteration":474,"passed_time":4.940366542,"remaining_time":5.460405125},
{"learn":[6.149418529],"iteration":475,"passed_time":4.953523292,"remaining_time":5.453038245},
{"learn":[6.148953121],"iteration":476,"passed_time":4.965558833,"remaining_time":5.444417756},
{"learn":[6.148491165],"iteration":477,"passed_time":4.978229917,"remaining_time":5.436477022},
{"learn":[6.147704337],"iteration":478,"passed_time":4.990806708,"remaining_time":5.428413977},
{"learn":[6.147424042],"iteration":479,"passed_time":5.004189333,"remaining_time":5.421205111},
{"learn":[6.145892481],"iteration":480,"passed_time":5.018117583,"remaining_time":5.414559305},
{"learn":[6.145830629],"iteration":481,"passed_time":5.033331875,"remaining_time":5.409265376},
{"learn":[6.145635418],"iteration":482,"passed_time":5.044997,"remaining_time":5.400131364},
{"learn":[6.145155861],"iteration":483,"passed_time":5.057872208,"remaining_time":5.392276982},
{"learn":[6.144240767],"iteration":484,"passed_time":5.070656875,"remaining_time":5.384305754},
{"learn":[6.143075455],"iteration":485,"passed_time":5.085951,"remaining_time":5.378968753},
{"learn":[6.1427397],"iteration":486,"passed_time":5.099738375,"remaining_time":5.372003668},
{"learn":[6.141190116],"iteration":487,"passed_time":5.115365833,"remaining_time":5.366941202},
{"learn":[6.13946618],"iteration":488,"passed_time":5.128510458,"remaining_time":5.35924099},
{"learn":[6.138708756],"iteration":489,"passed_time":5.145969833,"remaining_time":5.356009418},
{"learn":[6.138252857],"iteration":490,"passed_time":5.159647083,"remaining_time":5.348799115},
{"learn":[6.13816515],"iteration":491,"passed_time":5.175866208,"remaining_time":5.344187061},
{"learn":[6.137937638],"iteration":492,"passed_time":5.191184583,"remaining_time":5.33860159},
{"learn":[6.136675318],"iteration":493,"passed_time":5.210394042,"remaining_time":5.336962318},
{"learn":[6.136551049],"iteration":494,"passed_time":5.22621225,"remaining_time":5.331792295},
{"learn":[6.13607323],"iteration":495,"passed_time":5.239578375,"remaining_time":5.324087704},
{"learn":[6.135592846],"iteration":496,"passed_time":5.252604167,"remaining_time":5.316015887},
{"learn":[6.134371602],"iteration":497,"passed_time":5.266405042,"remaining_time":5.308705484},
{"learn":[6.133917453],"iteration":498,"passed_time":5.27914525,"remaining_time":5.300304149},
{"learn":[6.133392888],"iteration":499,"passed_time":5.293715417,"remaining_time":5.293715417},
{"learn":[6.133309715],"iteration":500,"passed_time":5.304269,"remaining_time":5.283094273},
{"learn":[6.133111321],"iteration":501,"passed_time":5.315501417,"remaining_time":5.273146824},
{"learn":[6.132337822],"iteration":502,"passed_time":5.327486917,"remaining_time":5.263938365},
{"learn":[6.132069311],"iteration":503,"passed_time":5.340997833,"remaining_time":5.25622009},
{"learn":[6.13113803],"iteration":504,"passed_time":5.351904792,"remaining_time":5.245926479},
{"learn":[6.130975771],"iteration":505,"passed_time":5.364172375,"remaining_time":5.236958801},
{"learn":[6.13076208],"iteration":506,"passed_time":5.3763625,"remaining_time":5.227902786},
{"learn":[6.129902033],"iteration":507,"passed_time":5.391296583,"remaining_time":5.221491967},
{"learn":[6.128316499],"iteration":508,"passed_time":5.403839542,"remaining_time":5.21274109},
{"learn":[6.127484545],"iteration":509,"passed_time":5.415976,"remaining_time":5.203584784},
{"learn":[6.127340874],"iteration":510,"passed_time":5.429451875,"remaining_time":5.195698565},
{"learn":[6.126076375],"iteration":511,"passed_time":5.445318,"remaining_time":5.190068719},
{"learn":[6.125284357],"iteration":512,"passed_time":5.45948325,"remaining_time":5.182784294},
{"learn":[6.124707069],"iteration":513,"passed_time":5.474182875,"remaining_time":5.17597836},
{"learn":[6.123082282],"iteration":514,"passed_time":5.488252167,"remaining_time":5.168548157},
{"learn":[6.122261513],"iteration":515,"passed_time":5.502514,"remaining_time":5.161272822},
{"learn":[6.121081051],"iteration":516,"passed_time":5.516324042,"remaining_time":5.153548379},
{"learn":[6.120835815],"iteration":517,"passed_time":5.530021458,"remaining_time":5.145695643},
{"learn":[6.120469154],"iteration":518,"passed_time":5.54113425,"remaining_time":5.135424999},
{"learn":[6.120006201],"iteration":519,"passed_time":5.552098458,"remaining_time":5.125013962},
{"learn":[6.118211752],"iteration":520,"passed_time":5.564102792,"remaining_time":5.115557077},
{"learn":[6.118164254],"iteration":521,"passed_time":5.57532475,"remaining_time":5.105374005},
{"learn":[6.117731464],"iteration":522,"passed_time":5.587333417,"remaining_time":5.095904474},
{"learn":[6.117085417],"iteration":523,"passed_time":5.600730917,"remaining_time":5.087686863},
{"learn":[6.116368889],"iteration":524,"passed_time":5.613208333,"remaining_time":5.078617063},
{"learn":[6.115131513],"iteration":525,"passed_time":5.627037417,"remaining_time":5.070752349},
{"learn":[6.11500875],"iteration":526,"passed_time":5.638863667,"remaining_time":5.06106739},
{"learn":[6.114854434],"iteration":527,"passed_time":5.6496035,"remaining_time":5.050403129},
{"learn":[6.114369541],"iteration":528,"passed_time":5.6617235,"remaining_time":5.040967426},
{"learn":[6.113296676],"iteration":529,"passed_time":5.67413775,"remaining_time":5.031782533},
{"learn":[6.112777727],"iteration":530,"passed_time":5.687375917,"remaining_time":5.023313192},
{"learn":[6.111443846],"iteration":531,"passed_time":5.704792792,"remaining_time":5.01850193},
{"learn":[6.110338507],"iteration":532,"passed_time":5.717957583,"remaining_time":5.009917808},
{"learn":[6.109804783],"iteration":533,"passed_time":5.731891833,"remaining_time":5.001988004},
{"learn":[6.109402919],"iteration":534,"passed_time":5.745588292,"remaining_time":4.993829076},
{"learn":[6.109227984],"iteration":535,"passed_time":5.759722167,"remaining_time":4.986028144},
{"learn":[6.107490396],"iteration":536,"passed_time":5.77321975,"remaining_time":4.977655017},
{"learn":[6.106877879],"iteration":537,"passed_time":5.78769875,"remaining_time":4.970105618},
{"learn":[6.106486075],"iteration":538,"passed_time":5.803373583,"remaining_time":4.963553287},
{"learn":[6.106105983],"iteration":539,"passed_time":5.817165167,"remaining_time":4.95536292},
{"learn":[6.10382314],"iteration":540,"passed_time":5.829284708,"remaining_time":4.945733237},
{"learn":[6.102456074],"iteration":541,"passed_time":5.842273083,"remaining_time":4.936828546},
{"learn":[6.101843369],"iteration":542,"passed_time":5.85939025,"remaining_time":4.931383691},
{"learn":[6.101594981],"iteration":543,"passed_time":5.870022375,"remaining_time":4.920459932},
{"learn":[6.100796286],"iteration":544,"passed_time":5.881851292,"remaining_time":4.910536399},
{"learn":[6.100437762],"iteration":545,"passed_time":5.896667917,"remaining_time":4.903090172},
{"learn":[6.099621976],"iteration":546,"passed_time":5.909841792,"remaining_time":4.894256548},
{"learn":[6.09948551],"iteration":547,"passed_time":5.923542875,"remaining_time":4.885841933},
{"learn":[6.098642874],"iteration":548,"passed_time":5.937443375,"remaining_time":4.87757188},
{"learn":[6.09773004],"iteration":549,"passed_time":5.952501792,"remaining_time":4.870228739},
{"learn":[6.0972005],"iteration":550,"passed_time":5.969135333,"remaining_time":4.864141134},
{"learn":[6.096426132],"iteration":551,"passed_time":5.98386275,"remaining_time":4.856468319},
{"learn":[6.096375481],"iteration":552,"passed_time":5.997670625,"remaining_time":4.848026708},
{"learn":[6.09555151],"iteration":553,"passed_time":6.010982917,"remaining_time":4.839166752},
{"learn":[6.095275349],"iteration":554,"passed_time":6.024640125,"remaining_time":4.830567307},
{"learn":[6.094965973],"iteration":555,"passed_time":6.0392525,"remaining_time":4.822712428},
{"learn":[6.093351707],"iteration":556,"passed_time":6.053015083,"remaining_time":4.814157418},
{"learn":[6.092399367],"iteration":557,"passed_time":6.066834083,"remaining_time":4.805628432},
{"learn":[6.090909913],"iteration":558,"passed_time":6.078700458,"remaining_time":4.795540075},
{"learn":[6.090773202],"iteration":559,"passed_time":6.09118225,"remaining_time":4.785928911},
{"learn":[6.090483933],"iteration":560,"passed_time":6.10296725,"remaining_time":4.775762251},
{"learn":[6.089066631],"iteration":561,"passed_time":6.115456208,"remaining_time":4.766138468},
{"learn":[6.088405923],"iteration":562,"passed_time":6.1268785,"remaining_time":4.755676562},
{"learn":[6.087044495],"iteration":563,"passed_time":6.141760708,"remaining_time":4.747885938},
{"learn":[6.086524381],"iteration":564,"passed_time":6.157776,"remaining_time":4.740942584},
{"learn":[6.085857079],"iteration":565,"passed_time":6.171862583,"remaining_time":4.732488271},
{"learn":[6.084460782],"iteration":566,"passed_time":6.19166375,"remaining_time":4.728378137},
{"learn":[6.084299968],"iteration":567,"passed_time":6.207379667,"remaining_time":4.721105662},
{"learn":[6.084237817],"iteration":568,"passed_time":6.221574542,"remaining_time":4.712651366},
{"learn":[6.084158085],"iteration":569,"passed_time":6.234618167,"remaining_time":4.703308442},
{"learn":[6.08333296],"iteration":570,"passed_time":6.246511792,"remaining_time":4.693088544},
{"learn":[6.083151951],"iteration":571,"passed_time":6.260348042,"remaining_time":4.684316367},
{"learn":[6.082352593],"iteration":572,"passed_time":6.274500292,"remaining_time":4.675761997},
{"learn":[6.081582395],"iteration":573,"passed_time":6.290437917,"remaining_time":4.668513158},
{"learn":[6.081446527],"iteration":574,"passed_time":6.301716458,"remaining_time":4.657790426},
{"learn":[6.081247344],"iteration":575,"passed_time":6.312852375,"remaining_time":4.646960776},
{"learn":[6.080327492],"iteration":576,"passed_time":6.324828667,"remaining_time":4.636746146},
{"learn":[6.080156263],"iteration":577,"passed_time":6.337705167,"remaining_time":4.627182665},
{"learn":[6.079972095],"iteration":578,"passed_time":6.349160208,"remaining_time":4.616574176},
{"learn":[6.079355311],"iteration":579,"passed_time":6.362529667,"remaining_time":4.607349069},
{"learn":[6.079117907],"iteration":580,"passed_time":6.373707542,"remaining_time":4.596529191},
{"learn":[6.077158046],"iteration":581,"passed_time":6.387178958,"remaining_time":4.587355334},
{"learn":[6.075726604],"iteration":582,"passed_time":6.399348917,"remaining_time":4.577235846},
{"learn":[6.075019112],"iteration":583,"passed_time":6.413849125,"remaining_time":4.56876924},
{"learn":[6.074814736],"iteration":584,"passed_time":6.42481775,"remaining_time":4.557776694},
{"learn":[6.074014779],"iteration":585,"passed_time":6.43785425,"remaining_time":4.548245153},
{"learn":[6.073454571],"iteration":586,"passed_time":6.450876208,"remaining_time":4.538691438},
{"learn":[6.073186275],"iteration":587,"passed_time":6.464341958,"remaining_time":4.529436882},
{"learn":[6.072312343],"iteration":588,"passed_time":6.476579875,"remaining_time":4.519311254},
{"learn":[6.070814762],"iteration":589,"passed_time":6.491256417,"remaining_time":4.510873103},
{"learn":[6.070213571],"iteration":590,"passed_time":6.5042115,"remaining_time":4.50122251},
{"learn":[6.069550956],"iteration":591,"passed_time":6.518485875,"remaining_time":4.492469995},
{"learn":[6.068637027],"iteration":592,"passed_time":6.531733958,"remaining_time":4.482994471},
{"learn":[6.068287755],"iteration":593,"passed_time":6.544440833,"remaining_time":4.473136327},
{"learn":[6.066956329],"iteration":594,"passed_time":6.556601958,"remaining_time":4.462897131},
{"learn":[6.066435816],"iteration":595,"passed_time":6.56946175,"remaining_time":4.453125079},
{"learn":[6.065795636],"iteration":596,"passed_time":6.582159083,"remaining_time":4.443233016},
{"learn":[6.06554096],"iteration":597,"passed_time":6.598078375,"remaining_time":4.435497503},
{"learn":[6.065282544],"iteration":598,"passed_time":6.613362417,"remaining_time":4.427309397},
{"learn":[6.063736288],"iteration":599,"passed_time":6.626541958,"remaining_time":4.417694639},
{"learn":[6.063527545],"iteration":600,"passed_time":6.640026917,"remaining_time":4.408270782},
{"learn":[6.063426166],"iteration":601,"passed_time":6.65467625,"remaining_time":4.399603235},
{"learn":[6.063191388],"iteration":602,"passed_time":6.665195458,"remaining_time":4.388196678},
{"learn":[6.063062835],"iteration":603,"passed_time":6.675917167,"remaining_time":4.376925825},
{"learn":[6.061968791],"iteration":604,"passed_time":6.687514208,"remaining_time":4.366228285},
{"learn":[6.06184849],"iteration":605,"passed_time":6.700181125,"remaining_time":4.356223372},
{"learn":[6.060032477],"iteration":606,"passed_time":6.714121917,"remaining_time":4.347034453},
{"learn":[6.059791112],"iteration":607,"passed_time":6.726636208,"remaining_time":4.336910187},
{"learn":[6.058719181],"iteration":608,"passed_time":6.74458375,"remaining_time":4.330266414},
{"learn":[6.058046011],"iteration":609,"passed_time":6.770490083,"remaining_time":4.328673988},
{"learn":[6.057746313],"iteration":610,"passed_time":6.782841667,"remaining_time":4.31837219},
{"learn":[6.057194847],"iteration":611,"passed_time":6.797241208,"remaining_time":4.309362073},
{"learn":[6.055639415],"iteration":612,"passed_time":6.809200917,"remaining_time":4.298794053},
{"learn":[6.055050612],"iteration":613,"passed_time":6.8217135,"remaining_time":4.288569073},
{"learn":[6.05363395],"iteration":614,"passed_time":6.835080667,"remaining_time":4.278871637},
{"learn":[6.052878045],"iteration":615,"passed_time":6.848923417,"remaining_time":4.269458753},
{"learn":[6.052332898],"iteration":616,"passed_time":6.861390458,"remaining_time":4.259177545},
{"learn":[6.052211407],"iteration":617,"passed_time":6.873710667,"remaining_time":4.248798503},
{"learn":[6.051459139],"iteration":618,"passed_time":6.888833833,"remaining_time":4.240138434},
{"learn":[6.050112119],"iteration":619,"passed_time":6.90492225,"remaining_time":4.232049121},
{"learn":[6.049774126],"iteration":620,"passed_time":6.919278125,"remaining_time":4.222876666},
{"learn":[6.049459963],"iteration":621,"passed_time":6.934907417,"remaining_time":4.21446142},
{"learn":[6.047996614],"iteration":622,"passed_time":6.949879958,"remaining_time":4.205625593},
{"learn":[6.04763071],"iteration":623,"passed_time":6.9667775,"remaining_time":4.197930032},
{"learn":[6.047622703],"iteration":624,"passed_time":6.979403875,"remaining_time":4.187642325},
{"learn":[6.047373856],"iteration":625,"passed_time":6.999151125,"remaining_time":4.181601471},
{"learn":[6.047212062],"iteration":626,"passed_time":7.015072125,"remaining_time":4.173240674},
{"learn":[6.046942994],"iteration":627,"passed_time":7.031684083,"remaining_time":4.165265094},
{"learn":[6.046672183],"iteration":628,"passed_time":7.043684583,"remaining_time":4.154542099},
{"learn":[6.046606689],"iteration":629,"passed_time":7.055683,"remaining_time":4.143813825},
{"learn":[6.046449878],"iteration":630,"passed_time":7.069392333,"remaining_time":4.134082046},
{"learn":[6.046193407],"iteration":631,"passed_time":7.083499333,"remaining_time":4.124569232},
{"learn":[6.04606209],"iteration":632,"passed_time":7.097116958,"remaining_time":4.114758173},
{"learn":[6.045780321],"iteration":633,"passed_time":7.110364417,"remaining_time":4.104721414},
{"learn":[6.045258995],"iteration":634,"passed_time":7.123636292,"remaining_time":4.094688577},
{"learn":[6.043869347],"iteration":635,"passed_time":7.136413958,"remaining_time":4.084362706},
{"learn":[6.043754172],"iteration":636,"passed_time":7.150423208,"remaining_time":4.074730965},
{"learn":[6.043281806],"iteration":637,"passed_time":7.166610792,"remaining_time":4.066321484},
{"learn":[6.042217246],"iteration":638,"passed_time":7.180105,"remaining_time":4.056366049},
{"learn":[6.041500388],"iteration":639,"passed_time":7.195347458,"remaining_time":4.047382945},
{"learn":[6.04134822],"iteration":640,"passed_time":7.207968208,"remaining_time":4.036911992},
{"learn":[6.040084405],"iteration":641,"passed_time":7.224925542,"remaining_time":4.028852561},
{"learn":[6.039982507],"iteration":642,"passed_time":7.237067208,"remaining_time":4.018091747},
{"learn":[6.039842442],"iteration":643,"passed_time":7.250663875,"remaining_time":4.008130962},
{"learn":[6.039780074],"iteration":644,"passed_time":7.265135292,"remaining_time":3.998640354},
{"learn":[6.039676139],"iteration":645,"passed_time":7.27945675,"remaining_time":3.989052151},
{"learn":[6.039412645],"iteration":646,"passed_time":7.292310458,"remaining_time":3.978648519},
{"learn":[6.039047334],"iteration":647,"passed_time":7.305206,"remaining_time":3.968260049},
{"learn":[6.038710927],"iteration":648,"passed_time":7.316949333,"remaining_time":3.957240703},
{"learn":[6.037105455],"iteration":649,"passed_time":7.329460375,"remaining_time":3.94663251},
{"learn":[6.036972392],"iteration":650,"passed_time":7.341262333,"remaining_time":3.935638332},
{"learn":[6.036248935],"iteration":651,"passed_time":7.35442925,"remaining_time":3.925370213},
{"learn":[6.034774407],"iteration":652,"passed_time":7.366201083,"remaining_time":3.914351877},
{"learn":[6.034052026],"iteration":653,"passed_time":7.379835375,"remaining_time":3.904316575},
{"learn":[6.033322079],"iteration":654,"passed_time":7.393021917,"remaining_time":3.894034445},
{"learn":[6.032972569],"iteration":655,"passed_time":7.406286083,"remaining_time":3.883784166},
{"learn":[6.032502302],"iteration":656,"passed_time":7.419638042,"remaining_time":3.873570545},
{"learn":[6.032270924],"iteration":657,"passed_time":7.4336025,"remaining_time":3.863665737},
{"learn":[6.032020508],"iteration":658,"passed_time":7.44692575,"remaining_time":3.853416814},
{"learn":[6.031920057],"iteration":659,"passed_time":7.460197625,"remaining_time":3.84313211},
{"learn":[6.031668844],"iteration":660,"passed_time":7.473608792,"remaining_time":3.832909804},
{"learn":[6.03141576],"iteration":661,"passed_time":7.486408292,"remaining_time":3.822365563},
{"learn":[6.031078544],"iteration":662,"passed_time":7.499796167,"remaining_time":3.812113587},
{"learn":[6.030949287],"iteration":663,"passed_time":7.513379083,"remaining_time":3.801950861},
{"learn":[6.030873166],"iteration":664,"passed_time":7.52441325,"remaining_time":3.790493893},
{"learn":[6.029853112],"iteration":665,"passed_time":7.541000042,"remaining_time":3.781822844},
{"learn":[6.028511394],"iteration":666,"passed_time":7.55506475,"remaining_time":3.771868908},
{"learn":[6.027837048],"iteration":667,"passed_time":7.570758,"remaining_time":3.76271206},
{"learn":[6.026975953],"iteration":668,"passed_time":7.584251292,"remaining_time":3.752447201},
{"learn":[6.026019074],"iteration":669,"passed_time":7.598174917,"remaining_time":3.74238466},
{"learn":[6.02598887],"iteration":670,"passed_time":7.611254792,"remaining_time":3.73189691},
{"learn":[6.025590263],"iteration":671,"passed_time":7.623475958,"remaining_time":3.720982313},
{"learn":[6.024729934],"iteration":672,"passed_time":7.635550208,"remaining_time":3.709992449},
{"learn":[6.02402971],"iteration":673,"passed_time":7.647891375,"remaining_time":3.699128469},
{"learn":[6.023302538],"iteration":674,"passed_time":7.6616575,"remaining_time":3.688946204},
{"learn":[6.022536533],"iteration":675,"passed_time":7.674683208,"remaining_time":3.678398461},
{"learn":[6.022443011],"iteration":676,"passed_time":7.694894125,"remaining_time":3.671271495},
{"learn":[6.021929484],"iteration":677,"passed_time":7.709263917,"remaining_time":3.661331831},
{"learn":[6.021848732],"iteration":678,"passed_time":7.722170125,"remaining_time":3.650687202},
{"learn":[6.021163738],"iteration":679,"passed_time":7.737643333,"remaining_time":3.641243922},
{"learn":[6.020822554],"iteration":680,"passed_time":7.749497167,"remaining_time":3.630087513},
{"learn":[6.020637396],"iteration":681,"passed_time":7.761692292,"remaining_time":3.619088195},
{"learn":[6.019723117],"iteration":682,"passed_time":7.77348625,"remaining_time":3.607899182},
{"learn":[6.018999535],"iteration":683,"passed_time":7.786536917,"remaining_time":3.597288985},
{"learn":[6.017849638],"iteration":684,"passed_time":7.797607667,"remaining_time":3.58576119},
{"learn":[6.01775079],"iteration":685,"passed_time":7.810760833,"remaining_time":3.575187903},
{"learn":[6.017477823],"iteration":686,"passed_time":7.824241083,"remaining_time":3.564756127},
{"learn":[6.015879017],"iteration":687,"passed_time":7.837117833,"remaining_time":3.554041808},
{"learn":[6.01559944],"iteration":688,"passed_time":7.849704375,"remaining_time":3.543190219},
{"learn":[6.015218717],"iteration":689,"passed_time":7.863741333,"remaining_time":3.532985237},
{"learn":[6.01515261],"iteration":690,"passed_time":7.87737325,"remaining_time":3.522588038},
{"learn":[6.014860786],"iteration":691,"passed_time":7.891813125,"remaining_time":3.512541102},
{"learn":[6.014776673],"iteration":692,"passed_time":7.911467667,"remaining_time":3.504791593},
{"learn":[6.014600776],"iteration":693,"passed_time":7.928272333,"remaining_time":3.495751202},
{"learn":[6.014335787],"iteration":694,"passed_time":7.940631458,"remaining_time":3.484737546},
{"learn":[6.014159182],"iteration":695,"passed_time":7.953717792,"remaining_time":3.474037656},
{"learn":[6.014106231],"iteration":696,"passed_time":7.964413875,"remaining_time":3.462291828},
{"learn":[6.013976823],"iteration":697,"passed_time":7.976454208,"remaining_time":3.451130617},
{"learn":[6.013832077],"iteration":698,"passed_time":7.988105292,"remaining_time":3.439799274},
{"learn":[6.013632892],"iteration":699,"passed_time":8.0012775,"remaining_time":3.429118929},
{"learn":[6.012982616],"iteration":700,"passed_time":8.014438333,"remaining_time":3.418426621},
{"learn":[6.012655442],"iteration":701,"passed_time":8.02787175,"remaining_time":3.407842994},
{"learn":[6.012615547],"iteration":702,"passed_time":8.040826583,"remaining_time":3.397049069},
{"learn":[6.012224849],"iteration":703,"passed_time":8.055756625,"remaining_time":3.38707949},
{"learn":[6.011032099],"iteration":704,"passed_time":8.070111917,"remaining_time":3.376855341},
{"learn":[6.009785348],"iteration":705,"passed_time":8.083004125,"remaining_time":3.366010216},
{"learn":[6.008576232],"iteration":706,"passed_time":8.095090167,"remaining_time":3.354825203},
{"learn":[6.008386752],"iteration":707,"passed_time":8.10959925,"remaining_time":3.344636979},
{"learn":[6.007938177],"iteration":708,"passed_time":8.122373,"remaining_time":3.33372432},
{"learn":[6.007726095],"iteration":709,"passed_time":8.137059875,"remaining_time":3.323587836},
{"learn":[6.006431371],"iteration":710,"passed_time":8.153165333,"remaining_time":3.314015164},
{"learn":[6.006310612],"iteration":711,"passed_time":8.168617625,"remaining_time":3.304159938},
{"learn":[6.005744647],"iteration":712,"passed_time":8.182085833,"remaining_time":3.293490371},
{"learn":[6.005667543],"iteration":713,"passed_time":8.195864917,"remaining_time":3.282937488},
{"learn":[6.005598146],"iteration":714,"passed_time":8.208571333,"remaining_time":3.271948014},
{"learn":[6.005474027],"iteration":715,"passed_time":8.222138208,"remaining_time":3.261295044},
{"learn":[6.005245474],"iteration":716,"passed_time":8.23480075,"remaining_time":3.250277005},
{"learn":[6.005242172],"iteration":717,"passed_time":8.246038708,"remaining_time":3.238694869},
{"learn":[6.005071693],"iteration":718,"passed_time":8.257912417,"remaining_time":3.227362154},
{"learn":[6.004471894],"iteration":719,"passed_time":8.2735355,"remaining_time":3.217486028},
{"learn":[6.003691771],"iteration":720,"passed_time":8.287550167,"remaining_time":3.206971562},
{"learn":[6.002279722],"iteration":721,"passed_time":8.302546958,"remaining_time":3.19682556},
{"learn":[6.001210896],"iteration":722,"passed_time":8.319002125,"remaining_time":3.187224881},
{"learn":[6.000992338],"iteration":723,"passed_time":8.335431458,"remaining_time":3.177595418},
{"learn":[6.000940247],"iteration":724,"passed_time":8.352058708,"remaining_time":3.168022269},
{"learn":[5.999617858],"iteration":725,"passed_time":8.372612208,"remaining_time":3.159911495},
{"learn":[5.99841412],"iteration":726,"passed_time":8.39590225,"remaining_time":3.152794105},
{"learn":[5.998286426],"iteration":727,"passed_time":8.416978333,"remaining_time":3.144805092},
{"learn":[5.997277722],"iteration":728,"passed_time":8.433187667,"remaining_time":3.134970998},
{"learn":[5.995697042],"iteration":729,"passed_time":8.457065625,"remaining_time":3.127955779},
{"learn":[5.99550017],"iteration":730,"passed_time":8.481009292,"remaining_time":3.120918604},
{"learn":[5.99535772],"iteration":731,"passed_time":8.507110625,"remaining_time":3.114625202},
{"learn":[5.994608118],"iteration":732,"passed_time":8.535865292,"remaining_time":3.109244247},
{"learn":[5.993727757],"iteration":733,"passed_time":8.553922417,"remaining_time":3.099922838},
{"learn":[5.992570545],"iteration":734,"passed_time":8.572778583,"remaining_time":3.090865748},
{"learn":[5.992365708],"iteration":735,"passed_time":8.601083875,"remaining_time":3.08517139},
{"learn":[5.991836286],"iteration":736,"passed_time":8.625610042,"remaining_time":3.078067084},
{"learn":[5.991241926],"iteration":737,"passed_time":8.648784083,"remaining_time":3.070435542},
{"learn":[5.991140776],"iteration":738,"passed_time":8.664192208,"remaining_time":3.06001917},
{"learn":[5.990117431],"iteration":739,"passed_time":8.6831105,"remaining_time":3.050822608},
{"learn":[5.989284284],"iteration":740,"passed_time":8.701297542,"remaining_time":3.041344215},
{"learn":[5.988197895],"iteration":741,"passed_time":8.72062825,"remaining_time":3.032240011},
{"learn":[5.98798561],"iteration":742,"passed_time":8.739813458,"remaining_time":3.023057953},
{"learn":[5.987190938],"iteration":743,"passed_time":8.756919375,"remaining_time":3.013133548},
{"learn":[5.986778274],"iteration":744,"passed_time":8.776036708,"remaining_time":3.003878336},
{"learn":[5.985185135],"iteration":745,"passed_time":8.795499667,"remaining_time":2.994714364},
{"learn":[5.98509013],"iteration":746,"passed_time":8.815204125,"remaining_time":2.98560461},
{"learn":[5.984987072],"iteration":747,"passed_time":8.838489958,"remaining_time":2.977673088},
{"learn":[5.984466647],"iteration":748,"passed_time":8.85533725,"remaining_time":2.967542924},
{"learn":[5.984437119],"iteration":749,"passed_time":8.887115458,"remaining_time":2.962371819},
{"learn":[5.984105171],"iteration":750,"passed_time":8.915895667,"remaining_time":2.956135847},
{"learn":[5.984074502],"iteration":751,"passed_time":8.947722708,"remaining_time":2.950844723},
{"learn":[5.983977737],"iteration":752,"passed_time":8.978134375,"remaining_time":2.945018845},
{"learn":[5.983340924],"iteration":753,"passed_time":8.995917458,"remaining_time":2.935007553},
{"learn":[5.982642606],"iteration":754,"passed_time":9.015677375,"remaining_time":2.925617161},
{"learn":[5.981662002],"iteration":755,"passed_time":9.048837667,"remaining_time":2.920524326},
{"learn":[5.981272333],"iteration":756,"passed_time":9.075240708,"remaining_time":2.913188233},
{"learn":[5.981114356],"iteration":757,"passed_time":9.09473475,"remaining_time":2.903596055},
{"learn":[5.980821982],"iteration":758,"passed_time":9.114297375,"remaining_time":2.893999562},
{"learn":[5.980739212],"iteration":759,"passed_time":9.143171625,"remaining_time":2.887317355},
{"learn":[5.980086214],"iteration":760,"passed_time":9.164906792,"remaining_time":2.878334722},
{"learn":[5.978913399],"iteration":761,"passed_time":9.183811542,"remaining_time":2.868434576},
{"learn":[5.978153878],"iteration":762,"passed_time":9.202643667,"remaining_time":2.858488269},
{"learn":[5.977293579],"iteration":763,"passed_time":9.226383708,"remaining_time":2.850034758},
{"learn":[5.977030348],"iteration":764,"passed_time":9.252124458,"remaining_time":2.842155879},
{"learn":[5.976938158],"iteration":765,"passed_time":9.270501,"remaining_time":2.831980723},
{"learn":[5.975890494],"iteration":766,"passed_time":9.28889425,"remaining_time":2.821789257},
{"learn":[5.97471997],"iteration":767,"passed_time":9.306049542,"remaining_time":2.811202466},
{"learn":[5.974232496],"iteration":768,"passed_time":9.324861833,"remaining_time":2.801096337},
{"learn":[5.973047042],"iteration":769,"passed_time":9.343536958,"remaining_time":2.790926624},
{"learn":[5.971955515],"iteration":770,"passed_time":9.363334292,"remaining_time":2.781068162},
{"learn":[5.97110768],"iteration":771,"passed_time":9.380470417,"remaining_time":2.770397999},
{"learn":[5.969309768],"iteration":772,"passed_time":9.402096833,"remaining_time":2.76102973},
{"learn":[5.968769807],"iteration":773,"passed_time":9.420416833,"remaining_time":2.750664347},
{"learn":[5.967801096],"iteration":774,"passed_time":9.441231208,"remaining_time":2.741002609},
{"learn":[5.967168976],"iteration":775,"passed_time":9.458095375,"remaining_time":2.730171861},
{"learn":[5.966170637],"iteration":776,"passed_time":9.4769715,"remaining_time":2.719903017},
{"learn":[5.966150496],"iteration":777,"passed_time":9.49406325,"remaining_time":2.709102881},
{"learn":[5.966056492],"iteration":778,"passed_time":9.512599708,"remaining_time":2.698696451},
{"learn":[5.965729718],"iteration":779,"passed_time":9.529126375,"remaining_time":2.687702311},
{"learn":[5.964688956],"iteration":780,"passed_time":9.54331575,"remaining_time":2.676038603},
{"learn":[5.964301872],"iteration":781,"passed_time":9.5597005,"remaining_time":2.664980446},
{"learn":[5.963143461],"iteration":782,"passed_time":9.572603458,"remaining_time":2.652943743},
{"learn":[5.962413711],"iteration":783,"passed_time":9.5902305,"remaining_time":2.642206362},
{"learn":[5.962039347],"iteration":784,"passed_time":9.611735,"remaining_time":2.632513408},
{"learn":[5.96108747],"iteration":785,"passed_time":9.626788417,"remaining_time":2.621033996},
{"learn":[5.959960914],"iteration":786,"passed_time":9.641652708,"remaining_time":2.609494316},
{"learn":[5.959232725],"iteration":787,"passed_time":9.657738333,"remaining_time":2.59827478},
{"learn":[5.957964588],"iteration":788,"passed_time":9.673457042,"remaining_time":2.586944786},
{"learn":[5.957152245],"iteration":789,"passed_time":9.693057958,"remaining_time":2.57663566},
{"learn":[5.956942284],"iteration":790,"passed_time":9.710003875,"remaining_time":2.56560153},
{"learn":[5.955959806],"iteration":791,"passed_time":9.726202083,"remaining_time":2.554356103},
{"learn":[5.955217906],"iteration":792,"passed_time":9.743155708,"remaining_time":2.543295374},
{"learn":[5.95459258],"iteration":793,"passed_time":9.760271,"remaining_time":2.532261746},
{"learn":[5.954017471],"iteration":794,"passed_time":9.776333042,"remaining_time":2.520941225},
{"learn":[5.952924217],"iteration":795,"passed_time":9.792438,"remaining_time":2.509619789},
{"learn":[5.95265807],"iteration":796,"passed_time":9.807301583,"remaining_time":2.497970165},
{"learn":[5.951174531],"iteration":797,"passed_time":9.823865125,"remaining_time":2.486742801},
{"learn":[5.950649857],"iteration":798,"passed_time":9.838393458,"remaining_time":2.474990094},
{"learn":[5.95010932],"iteration":799,"passed_time":9.855530833,"remaining_time":2.463882708},
{"learn":[5.950027759],"iteration":800,"passed_time":9.876613125,"remaining_time":2.453740339},
{"learn":[5.949999319],"iteration":801,"passed_time":9.891217375,"remaining_time":2.441971372},
{"learn":[5.949435573],"iteration":802,"passed_time":9.912349167,"remaining_time":2.431796744},
{"learn":[5.948158528],"iteration":803,"passed_time":9.938469583,"remaining_time":2.422810993},
{"learn":[5.947609178],"iteration":804,"passed_time":9.954747833,"remaining_time":2.411398543},
{"learn":[5.94754608],"iteration":805,"passed_time":9.969376708,"remaining_time":2.399577024},
{"learn":[5.947133906],"iteration":806,"passed_time":9.983837958,"remaining_time":2.387708458},
{"learn":[5.9468934],"iteration":807,"passed_time":10.00183221,"remaining_time":2.376673},
{"learn":[5.946262416],"iteration":808,"passed_time":10.01829379,"remaining_time":2.365258485},
{"learn":[5.94603023],"iteration":809,"passed_time":10.03608792,"remaining_time":2.354144079},
{"learn":[5.945917906],"iteration":810,"passed_time":10.05300138,"remaining_time":2.342807965},
{"learn":[5.94580908],"iteration":811,"passed_time":10.07057263,"remaining_time":2.331610411},
{"learn":[5.944882238],"iteration":812,"passed_time":10.089626,"remaining_time":2.320738084},
{"learn":[5.944511192],"iteration":813,"passed_time":10.10594563,"remaining_time":2.30922099},
{"learn":[5.944241595],"iteration":814,"passed_time":10.12277017,"remaining_time":2.297806725},
{"learn":[5.943166103],"iteration":815,"passed_time":10.14445246,"remaining_time":2.287474574},
{"learn":[5.942855664],"iteration":816,"passed_time":10.15822892,"remaining_time":2.275343809},
{"learn":[5.942604958],"iteration":817,"passed_time":10.17427296,"remaining_time":2.263713543},
{"learn":[5.942384305],"iteration":818,"passed_time":10.20012825,"remaining_time":2.254240798},
{"learn":[5.942236347],"iteration":819,"passed_time":10.23685279,"remaining_time":2.247114027},
{"learn":[5.94191391],"iteration":820,"passed_time":10.27683475,"remaining_time":2.24062536},
{"learn":[5.941607409],"iteration":821,"passed_time":10.29488675,"remaining_time":2.229306377},
{"learn":[5.941307244],"iteration":822,"passed_time":10.31087417,"remaining_time":2.217527008},
{"learn":[5.940395983],"iteration":823,"passed_time":10.32929667,"remaining_time":2.20625754},
{"learn":[5.939162237],"iteration":824,"passed_time":10.34873579,"remaining_time":2.19518638},
{"learn":[5.938895314],"iteration":825,"passed_time":10.36818138,"remaining_time":2.184096319},
{"learn":[5.937655023],"iteration":826,"passed_time":10.38711483,"remaining_time":2.172878919},
{"learn":[5.937469449],"iteration":827,"passed_time":10.40751913,"remaining_time":2.161948417},
{"learn":[5.937326068],"iteration":828,"passed_time":10.42761946,"remaining_time":2.150932361},
{"learn":[5.936400135],"iteration":829,"passed_time":10.44880988,"remaining_time":2.140117685},
{"learn":[5.936286592],"iteration":830,"passed_time":10.4742195,"remaining_time":2.130136096},
{"learn":[5.936169686],"iteration":831,"passed_time":10.49346046,"remaining_time":2.118871823},
{"learn":[5.935552042],"iteration":832,"passed_time":10.51135121,"remaining_time":2.107317709},
{"learn":[5.935120782],"iteration":833,"passed_time":10.52833671,"remaining_time":2.095568218},
{"learn":[5.935078664],"iteration":834,"passed_time":10.54337808,"remaining_time":2.083422016},
{"learn":[5.933504841],"iteration":835,"passed_time":10.55815746,"remaining_time":2.071217492},
{"learn":[5.933269574],"iteration":836,"passed_time":10.57001562,"remaining_time":2.058437929},
{"learn":[5.932812923],"iteration":837,"passed_time":10.58197254,"remaining_time":2.045679656},
{"learn":[5.93157289],"iteration":838,"passed_time":10.59379721,"remaining_time":2.032897915},
{"learn":[5.931560195],"iteration":839,"passed_time":10.60547667,"remaining_time":2.020090794},
{"learn":[5.931425145],"iteration":840,"passed_time":10.61833142,"remaining_time":2.007508556},
{"learn":[5.931224237],"iteration":841,"passed_time":10.6317465,"remaining_time":1.995030816},
{"learn":[5.930798701],"iteration":842,"passed_time":10.64356388,"remaining_time":1.982253296},
{"learn":[5.929772323],"iteration":843,"passed_time":10.66051158,"remaining_time":1.970426312},
{"learn":[5.928665768],"iteration":844,"passed_time":10.69877408,"remaining_time":1.962497021},
{"learn":[5.928381663],"iteration":845,"passed_time":10.71362558,"remaining_time":1.950234444},
{"learn":[5.927232911],"iteration":846,"passed_time":10.72724413,"remaining_time":1.937743036},
{"learn":[5.927005007],"iteration":847,"passed_time":10.73984933,"remaining_time":1.925067333},
{"learn":[5.926871114],"iteration":848,"passed_time":10.75210696,"remaining_time":1.912329977},
{"learn":[5.926075252],"iteration":849,"passed_time":10.76578133,"remaining_time":1.899843765},
{"learn":[5.92593376],"iteration":850,"passed_time":10.77643779,"remaining_time":1.886826358},
{"learn":[5.925912543],"iteration":851,"passed_time":10.78722238,"remaining_time":1.873836751},
{"learn":[5.925900769],"iteration":852,"passed_time":10.79729767,"remaining_time":1.860730079},
{"learn":[5.925471862],"iteration":853,"passed_time":10.81037517,"remaining_time":1.848143764},
{"learn":[5.925410075],"iteration":854,"passed_time":10.8225515,"remaining_time":1.835403471},
{"learn":[5.925323882],"iteration":855,"passed_time":10.833732,"remaining_time":1.822496972},
{"learn":[5.924749726],"iteration":856,"passed_time":10.84811854,"remaining_time":1.810129465},
{"learn":[5.924614718],"iteration":857,"passed_time":10.86503175,"remaining_time":1.798175418},
{"learn":[5.924109273],"iteration":858,"passed_time":10.87928446,"remaining_time":1.785773118},
{"learn":[5.924082372],"iteration":859,"passed_time":10.89309667,"remaining_time":1.773294806},
{"learn":[5.922936589],"iteration":860,"passed_time":10.90744204,"remaining_time":1.76089947},
{"learn":[5.921851171],"iteration":861,"passed_time":10.92334317,"remaining_time":1.748748674},
{"learn":[5.921745386],"iteration":862,"passed_time":10.94034379,"remaining_time":1.736763731},
{"learn":[5.920806235],"iteration":863,"passed_time":10.9648225,"remaining_time":1.725944282},
{"learn":[5.92060471],"iteration":864,"passed_time":10.97906796,"remaining_time":1.713496155},
{"learn":[5.919496831],"iteration":865,"passed_time":10.99436354,"remaining_time":1.701206368},
{"learn":[5.91839772],"iteration":866,"passed_time":11.00669758,"remaining_time":1.688455339},
{"learn":[5.918311995],"iteration":867,"passed_time":11.01824933,"remaining_time":1.675586304},
{"learn":[5.917084693],"iteration":868,"passed_time":11.02886792,"remaining_time":1.662579628},
{"learn":[5.916990822],"iteration":869,"passed_time":11.04176267,"remaining_time":1.649918559},
{"learn":[5.916883696],"iteration":870,"passed_time":11.0540025,"remaining_time":1.637159957},
{"learn":[5.915867812],"iteration":871,"passed_time":11.06712133,"remaining_time":1.624531572},
{"learn":[5.915113351],"iteration":872,"passed_time":11.07960029,"remaining_time":1.611808977},
{"learn":[5.915046954],"iteration":873,"passed_time":11.09314396,"remaining_time":1.599240433},
{"learn":[5.914943643],"iteration":874,"passed_time":11.10530667,"remaining_time":1.586472381},
{"learn":[5.914169787],"iteration":875,"passed_time":11.12075154,"remaining_time":1.57417031},
{"learn":[5.912979722],"iteration":876,"passed_time":11.14588154,"remaining_time":1.563219418},
{"learn":[5.912943342],"iteration":877,"passed_time":11.16540417,"remaining_time":1.551457071},
{"learn":[5.911732149],"iteration":878,"passed_time":11.18522858,"remaining_time":1.53971861},
{"learn":[5.910943592],"iteration":879,"passed_time":11.19885413,"remaining_time":1.527116472},
{"learn":[5.910764943],"iteration":880,"passed_time":11.21066558,"remaining_time":1.514266974},
{"learn":[5.910674999],"iteration":881,"passed_time":11.22383613,"remaining_time":1.501601658},
{"learn":[5.910560394],"iteration":882,"passed_time":11.23490421,"remaining_time":1.488656617},
{"learn":[5.910491315],"iteration":883,"passed_time":11.24742075,"remaining_time":1.47590589},
{"learn":[5.910394825],"iteration":884,"passed_time":11.25892404,"remaining_time":1.463024028},
{"learn":[5.910330408],"iteration":885,"passed_time":11.27380217,"remaining_time":1.450579511},
{"learn":[5.909371526],"iteration":886,"passed_time":11.288279,"remaining_time":1.438078384},
{"learn":[5.909221039],"iteration":887,"passed_time":11.30518142,"remaining_time":1.425878737},
{"learn":[5.909145569],"iteration":888,"passed_time":11.32536283,"remaining_time":1.414077924},
{"learn":[5.909077003],"iteration":889,"passed_time":11.33877229,"remaining_time":1.401421294},
{"learn":[5.908161461],"iteration":890,"passed_time":11.35519192,"remaining_time":1.389131222},
{"learn":[5.907951596],"iteration":891,"passed_time":11.37071021,"remaining_time":1.376722761},
{"learn":[5.906564305],"iteration":892,"passed_time":11.38420325,"remaining_time":1.364064667},
{"learn":[5.905555792],"iteration":893,"passed_time":11.39897313,"remaining_time":1.351556098},
{"learn":[5.904473357],"iteration":894,"passed_time":11.41341267,"remaining_time":1.339003721},
{"learn":[5.904027889],"iteration":895,"passed_time":11.42817888,"remaining_time":1.326485048},
{"learn":[5.903921373],"iteration":896,"passed_time":11.44126075,"remaining_time":1.313767957},
{"learn":[5.903630391],"iteration":897,"passed_time":11.45355479,"remaining_time":1.300960567},
{"learn":[5.903546355],"iteration":898,"passed_time":11.46557167,"remaining_time":1.288123179},
{"learn":[5.902297319],"iteration":899,"passed_time":11.47649838,"remaining_time":1.275166486},
{"learn":[5.901819684],"iteration":900,"passed_time":11.48916504,"remaining_time":1.262405482},
{"learn":[5.900439582],"iteration":901,"passed_time":11.50310221,"remaining_time":1.249782723},
{"learn":[5.900210367],"iteration":902,"passed_time":11.515406,"remaining_time":1.236981597},
{"learn":[5.900058839],"iteration":903,"passed_time":11.52827842,"remaining_time":1.224241956},
{"learn":[5.899406001],"iteration":904,"passed_time":11.54121671,"remaining_time":1.211508936},
{"learn":[5.898975593],"iteration":905,"passed_time":11.55558979,"remaining_time":1.198924327},
{"learn":[5.898609607],"iteration":906,"passed_time":11.57008204,"remaining_time":1.186347993},
{"learn":[5.897973248],"iteration":907,"passed_time":11.58425233,"remaining_time":1.173734818},
{"learn":[5.897017046],"iteration":908,"passed_time":11.59809488,"remaining_time":1.161085406},
{"learn":[5.89627838],"iteration":909,"passed_time":11.61350483,"remaining_time":1.14858839},
{"learn":[5.8945965],"iteration":910,"passed_time":11.62660117,"remaining_time":1.13585895},
{"learn":[5.894446287],"iteration":911,"passed_time":11.63951542,"remaining_time":1.123111137},
{"learn":[5.893490059],"iteration":912,"passed_time":11.65442933,"remaining_time":1.110553507},
{"learn":[5.892727493],"iteration":913,"passed_time":11.671024,"remaining_time":1.098148867},
{"learn":[5.892042313],"iteration":914,"passed_time":11.68547112,"remaining_time":1.085535569},
{"learn":[5.891355835],"iteration":915,"passed_time":11.69995787,"remaining_time":1.072921901},
{"learn":[5.890404756],"iteration":916,"passed_time":11.71368879,"remaining_time":1.060235736},
{"learn":[5.890225795],"iteration":917,"passed_time":11.72829462,"remaining_time":1.047625446},
{"learn":[5.889577617],"iteration":918,"passed_time":11.73998312,"remaining_time":1.034753681},
{"learn":[5.889467397],"iteration":919,"passed_time":11.75256746,"remaining_time":1.021962388},
{"learn":[5.888528137],"iteration":920,"passed_time":11.76493571,"remaining_time":1.009153009},
{"learn":[5.888446432],"iteration":921,"passed_time":11.78701092,"remaining_time":0.9971657825},
{"learn":[5.888242205],"iteration":922,"passed_time":11.79962479,"remaining_time":0.9843673987},
{"learn":[5.887375733],"iteration":923,"passed_time":11.81246546,"remaining_time":0.971588068},
{"learn":[5.887045095],"iteration":924,"passed_time":11.82388783,"remaining_time":0.9586936081},
{"learn":[5.886919958],"iteration":925,"passed_time":11.83571342,"remaining_time":0.9458345495},
{"learn":[5.886383589],"iteration":926,"passed_time":11.84850342,"remaining_time":0.9330536671},
{"learn":[5.886133356],"iteration":927,"passed_time":11.861714,"remaining_time":0.9203053966},
{"learn":[5.885960693],"iteration":928,"passed_time":11.87328517,"remaining_time":0.9074308362},
{"learn":[5.885934084],"iteration":929,"passed_time":11.88496025,"remaining_time":0.8945669005},
{"learn":[5.885834391],"iteration":930,"passed_time":11.89745842,"remaining_time":0.8817665207},
{"learn":[5.884890357],"iteration":931,"passed_time":11.91342537,"remaining_time":0.8692198771},
{"learn":[5.88456677],"iteration":932,"passed_time":11.92853221,"remaining_time":0.856604135},
{"learn":[5.884416451],"iteration":933,"passed_time":11.94254996,"remaining_time":0.8439060998},
{"learn":[5.884193011],"iteration":934,"passed_time":11.95434838,"remaining_time":0.8310509566},
{"learn":[5.883671721],"iteration":935,"passed_time":11.96847871,"remaining_time":0.8183575185},
{"learn":[5.882897779],"iteration":936,"passed_time":11.98240104,"remaining_time":0.8056470284},
{"learn":[5.882851129],"iteration":937,"passed_time":11.99760296,"remaining_time":0.7930185324},
{"learn":[5.882719274],"iteration":938,"passed_time":12.01276746,"remaining_time":0.7803821246},
{"learn":[5.882658522],"iteration":939,"passed_time":12.02839483,"remaining_time":0.767769883},
{"learn":[5.882549594],"iteration":940,"passed_time":12.04845687,"remaining_time":0.7554292833},
{"learn":[5.882200801],"iteration":941,"passed_time":12.06668987,"remaining_time":0.7429596738},
{"learn":[5.88076015],"iteration":942,"passed_time":12.08430679,"remaining_time":0.7304406014},
{"learn":[5.880670051],"iteration":943,"passed_time":12.09714067,"remaining_time":0.7176269887},
{"learn":[5.879308933],"iteration":944,"passed_time":12.1099355,"remaining_time":0.7048110608},
{"learn":[5.87926001],"iteration":945,"passed_time":12.12334696,"remaining_time":0.6920303761},
{"learn":[5.877938048],"iteration":946,"passed_time":12.13653525,"remaining_time":0.6792358693},
{"learn":[5.877753492],"iteration":947,"passed_time":12.15061254,"remaining_time":0.6664892955},
{"learn":[5.877641634],"iteration":948,"passed_time":12.16449142,"remaining_time":0.6537292542},
{"learn":[5.8767393],"iteration":949,"passed_time":12.17950921,"remaining_time":0.6410268004},
{"learn":[5.876255019],"iteration":950,"passed_time":12.19534992,"remaining_time":0.6283618779},
{"learn":[5.875633325],"iteration":951,"passed_time":12.21038683,"remaining_time":0.6156497563},
{"learn":[5.875611249],"iteration":952,"passed_time":12.22633612,"remaining_time":0.6029777522},
{"learn":[5.875098853],"iteration":953,"passed_time":12.24252287,"remaining_time":0.5903103273},
{"learn":[5.874639782],"iteration":954,"passed_time":12.26164987,"remaining_time":0.5777740779},
{"learn":[5.873545926],"iteration":955,"passed_time":12.280182,"remaining_time":0.5651966611},
{"learn":[5.873269603],"iteration":956,"passed_time":12.29529733,"remaining_time":0.5524532762},
{"learn":[5.872416935],"iteration":957,"passed_time":12.30910317,"remaining_time":0.5396475292},
{"learn":[5.871580406],"iteration":958,"passed_time":12.32018558,"remaining_time":0.5267232627},
{"learn":[5.871440203],"iteration":959,"passed_time":12.33415058,"remaining_time":0.513922941},
{"learn":[5.871426903],"iteration":960,"passed_time":12.34555983,"remaining_time":0.5010164761},
{"learn":[5.871199312],"iteration":961,"passed_time":12.3578525,"remaining_time":0.4881480198},
{"learn":[5.870699715],"iteration":962,"passed_time":12.37314296,"remaining_time":0.4753959392},
{"learn":[5.869705664],"iteration":963,"passed_time":12.38723033,"remaining_time":0.4625936639},
{"learn":[5.869071601],"iteration":964,"passed_time":12.39871417,"remaining_time":0.4496942962},
{"learn":[5.86750971],"iteration":965,"passed_time":12.41301954,"remaining_time":0.4368971681},
{"learn":[5.867178736],"iteration":966,"passed_time":12.42585183,"remaining_time":0.4240466499},
{"learn":[5.867152209],"iteration":967,"passed_time":12.43985654,"remaining_time":0.411234927},
{"learn":[5.866483915],"iteration":968,"passed_time":12.45412413,"remaining_time":0.3984291516},
{"learn":[5.866062048],"iteration":969,"passed_time":12.46788133,"remaining_time":0.3856045773},
{"learn":[5.865907746],"iteration":970,"passed_time":12.48215517,"remaining_time":0.3727935117},
{"learn":[5.864998339],"iteration":971,"passed_time":12.49775254,"remaining_time":0.3600175629},
{"learn":[5.863841251],"iteration":972,"passed_time":12.51029042,"remaining_time":0.347150916},
{"learn":[5.863187033],"iteration":973,"passed_time":12.52570663,"remaining_time":0.3343617785},
{"learn":[5.862998674],"iteration":974,"passed_time":12.53876479,"remaining_time":0.3215067895},
{"learn":[5.862369882],"iteration":975,"passed_time":12.55217246,"remaining_time":0.3086599785},
{"learn":[5.861817672],"iteration":976,"passed_time":12.56396367,"remaining_time":0.2957739655},
{"learn":[5.861035213],"iteration":977,"passed_time":12.57613379,"remaining_time":0.2828987151},
{"learn":[5.860516614],"iteration":978,"passed_time":12.58831733,"remaining_time":0.2700251931},
{"learn":[5.86028784],"iteration":979,"passed_time":12.60021354,"remaining_time":0.2571472151},
{"learn":[5.859748422],"iteration":980,"passed_time":12.61158046,"remaining_time":0.2442609875},
{"learn":[5.859436146],"iteration":981,"passed_time":12.625714,"remaining_time":0.2314285662},
{"learn":[5.858436462],"iteration":982,"passed_time":12.63918417,"remaining_time":0.2185820253},
{"learn":[5.858397361],"iteration":983,"passed_time":12.65205538,"remaining_time":0.2057244776},
{"learn":[5.857225765],"iteration":984,"passed_time":12.66455596,"remaining_time":0.1928612582},
{"learn":[5.855873825],"iteration":985,"passed_time":12.67884992,"remaining_time":0.1800242382},
{"learn":[5.855542217],"iteration":986,"passed_time":12.69152971,"remaining_time":0.1671630053},
{"learn":[5.85460948],"iteration":987,"passed_time":12.70585646,"remaining_time":0.1543221432},
{"learn":[5.854393499],"iteration":988,"passed_time":12.71882392,"remaining_time":0.1414631578},
{"learn":[5.853832524],"iteration":989,"passed_time":12.733744,"remaining_time":0.1286236768},
{"learn":[5.853641261],"iteration":990,"passed_time":12.74597413,"remaining_time":0.1157555672},
{"learn":[5.853126968],"iteration":991,"passed_time":12.76185138,"remaining_time":0.1029181563},
{"learn":[5.852671079],"iteration":992,"passed_time":12.79133179,"remaining_time":0.09017051615},
{"learn":[5.852019647],"iteration":993,"passed_time":12.80315275,"remaining_time":0.07728261217},
{"learn":[5.851378214],"iteration":994,"passed_time":12.8146575,"remaining_time":0.06439526382},
{"learn":[5.850714549],"iteration":995,"passed_time":12.82625971,"remaining_time":0.05151108317},
{"learn":[5.850540472],"iteration":996,"passed_time":12.83819446,"remaining_time":0.0386304748},
{"learn":[5.849466643],"iteration":997,"passed_time":12.85117046,"remaining_time":0.02575384861},
{"learn":[5.849401093],"iteration":998,"passed_time":12.86177554,"remaining_time":0.01287465019},
{"learn":[5.849202032],"iteration":999,"passed_time":12.87320679,"remaining_time":0}
]}